Workbook
Name IQ_CH: 110000
Name IQ_CQ: 5000
Name IQ_CY: 10000
Name IQ_DAILY: 500000
Name IQ_FH: 100000
Name IQ_FQ: 500
Name IQ_FY: 1000
Name IQ_LTM: 2000
Name IQ_MONTH: 15000
Name IQ_NTM: 6000
Name IQ_WEEK: 50000
Name IQ_YTD: 3000
Name UPDATE: 'Data Sheet'!$E$1

Sheet DCF>

Sheet WACC
B3: Weighted Average Cost of Capital
B5: All figures are in INR unless specified
B7: Peer Comps
I8: Debt/ | J8: Debt / | K8: Levered | L8: Unlevered
B9: Name of Company | E9: Country | F9: Total Debt | G9: Total Equity | H9: Tax Rate | I9: Equity | J9: Capital | K9: Beta 2 | L9: Beta 3
B11: Tata Motors | E11: India | F11: ='Beta comp'!D11 -> 431.9 | G11: ='Beta comp'!F11 -> 159039.89 | H11: 0.3 | I11: =F11/G11 -> 0.0027156709 | J11: =F11/(F11+G11) -> 0.002708316 | K11: 1.03 | L11: =K11/(1+(1-H11)) -> 0.60588235
B12: Hitachi Energy | E12: India | F12: ='Beta comp'!D7 -> 86.1 | G12: ='Beta comp'!F7 -> 151390.04 | H12: 0.3 | I12: =F12/G12 -> 0.00056872962 | J12: =F12/(F12+G12) -> 0.00056840635 | K12: 1.33 | L12: =K12/(1+(1-H12)) -> 0.78235294
B13: CG Power & Ind | E13: India | F13: ='Beta comp'!D8 -> 118.39 | G13: ='Beta comp'!F8 -> 148378.8 | H13: 0.3 | I13: =F13/G13 -> 0.00079789026 | J13: =F13/(F13+G13) -> 0.00079725414 | K13: 1.24 | L13: =K13/(1+(1-H13)) -> 0.72941176
B14: A B B | E14: India | F14: ='Beta comp'!D9 -> 84.82 | G14: ='Beta comp'!F9 -> 148187.53 | H14: 0.3 | I14: =F14/G14 -> 0.00057238284 | J14: =F14/(F14+G14) -> 0.00057205541 | K14: 1.19 | L14: =K14/(1+(1-H14)) -> 0.7
B15: Polycab India | E15: India | F15: ='Beta comp'!D10 -> 235.52 | G15: ='Beta comp'!F10 -> 143570.27 | H15: 0.3 | I15: =F15/G15 -> 0.001640451 | J15: =F15/(F15+G15) -> 0.0016377644 | K15: 1.4 | L15: =K15/(1+(1-H15)) -> 0.82352941
G17: Average | H17: =AVERAGE(H11:H15) -> 0.3 | I17: =AVERAGE(I11:I15) -> 0.0012590249 | J17: =AVERAGE(J11:J15) -> 0.0012567593 | K17: =AVERAGE(K11:K15) -> 1.238 | L17: =AVERAGE(L11:L15) -> 0.72823529
G18: Median | H18: =MEDIAN(H11:H15) -> 0.3 | I18: =MEDIAN(I11:I15) -> 0.00079789026 | J18: =MEDIAN(J11:J15) -> 0.00079725414 | K18: =MEDIAN(K11:K15) -> 1.24 | L18: =MEDIAN(L11:L15) -> 0.72941176
B20: Cost of Debt | H20: Cost of Equity
B22: Pre-tax Cost of Debt | F22: =874/5615 -> 0.1556545 | H22: Risk free Rate | K22: 0.0677
B23: Tax Rate | F23: =H11 -> 0.3 | H23: Equity risk premium | K23: =Rm!G8-WACC!K22 -> 0.083792308
B24: Post-tax Cost of Debt | F24: =F22*(1-F23) -> 0.10895815 | H24: Levered Beta | K24: =L32 -> 0.94795994
H25: Cost of Equity | K25: =K22+K23*K24 -> 0.14713175
B27: Capital Structure | H27: Levered Beta
E29: Current | F29: Target | H29: Comps Median Unlevered Beta | L29: =L18 -> 0.72941176
B30: Total Debt | D30: =F11 -> 431.9 | E30: =D30/D32 -> 0.002708316 | F30: =J17 -> 0.0012567593 | H30: Target Debt / Equity | L30: =F34 -> 0.0012583407
B31: Market Capitalization | D31: =G11 -> 159039.89 | E31: =D31/D32 -> 0.99729168 | F31: =F32-F30 -> 0.99874324 | H31: Tax Rate | L31: =H15 -> 0.3
B32: Total Capital | D32: =SUM(D30:D31) -> 159471.79 | E32: =SUM(E30:E31) -> 1 | F32: =E32 -> 1 | H32: Levered Beta | L32: =L29*(1+(1-L30)*L31) -> 0.94795994
B34: Debt / Equity | E34: =E30/E31 -> 0.0027156709 | F34: =F30/F31 -> 0.0012583407 | H34: Weighted Average Cost of Capital
B36: 1. Tax Rate considered as Marginal Tax Rate for the country | K36: Total Cost | L36: Total Weight
B37: 2. Levered Beta is based on 2 year weekly data | H37: Debt | K37: =F24 -> 0.10895815 | L37: =F30 -> 0.0012567593
B38: 3. Unlevered Beta = Levered Beta/(1+(1-Tax Rate) x Debt/Equity) | H38: Equity | K38: =K25 -> 0.14713175 | L38: =F31 -> 0.99874324
B39: 4. Levered Beta = Unlevered Beta*(1+(1-Tax Rate) x Debt/Equity) | H39: Weighted Average Cost of Capital | L39: =SUMPRODUCT(K37:K38,L37:L38) -> 0.14708378

Sheet DATA1>
D3: Debt | E3: d/e | F3: e
C4: Cummins India | D4: 36.51 | E4: 0 | F4: 55.44 | G4: 156396.24
C5: Hitachi Energy | D5: 86.1 | E5: 0.02 | F5: 8.92 | G5: 151390.04
C6: CG Power & Ind | D6: 118.39 | E6: 0.01 | F6: 314.99 | G6: 148378.8
C7: A B B | D7: 84.82 | E7: 0.01 | F7: 42.38 | G7: 148187.53
C8: Polycab India | D8: 235.52 | E8: 0.02 | F8: 150.55

Sheet Beta comp
B4: S.No. | C4: Name | D4: Debt Rs.Cr. | E4: Debt / Eq | F4: Mar Cap Rs.Cr.
B6: 5 | C6: Cummins India | D6: 36.51 | E6: 0 | F6: 156396.24
B7: 6 | C7: Hitachi Energy | D7: 86.1 | E7: 0.02 | F7: 151390.04
B8: 7 | C8: CG Power & Ind | D8: 118.39 | E8: 0.01 | F8: 148378.8
B9: 8 | C9: A B B | D9: 84.82 | E9: 0.01 | F9: 148187.53
B10: 9 | C10: Polycab India | D10: 235.52 | E10: 0.02 | F10: 143570.27
B11: 10 | C11: Tata Motors | D11: 431.9 | E11: 0.44 | F11: 159039.89

Sheet Rm
B3: Return on Market | D3: (Used Nifty 50 return table from primeinvestor.in)
B5: Year | C5: Annual
B6: 2000 | C6: -0.1465 | E6: Average Return on Market | G6: =AVERAGE(C6:C31) -> 0.15149231
B7: 2001 | C7: -0.1618 | E7: Dividend yield | G7: 1.30% 1
B8: 2002 | C8: 0.0325 | E8: Total Reurn on Market | G8: =SUM(G6:G7) -> 0.15149231
B9: 2003 | C9: 0.719
B10: 2004 | C10: 0.1068
B11: 2005 | C11: 0.3634
B12: 2006 | C12: 0.3983
B13: 2007 | C13: 0.5477
B14: 2008 | C14: -0.5179
B15: 2009 | C15: 0.7576
B16: 2010 | C16: 0.1795
B17: 2011 | C17: -0.2462
B18: 2012 | C18: 0.277
B19: 2013 | C19: 0.0676
B20: 2014 | C20: 0.3139
... B31: 2025 | C31: 0.1051

Sheet Intrinsic growth
B4: Calculation of ROIC | D4: =RawFS!F9 -> 43160 | E4: =RawFS!G9 -> 43525 | F4: =RawFS!H9 -> 43891 | G4: =RawFS!I9 -> 44256 | H4: =RawFS!J9 -> 44621
B6: Current Assests
B7: =RawFS!B39 -> Inventories | D7: =RawFS!F39 -> 42138 | E7: =RawFS!G39 -> 39014 | F7: =RawFS!H39 -> 37457 | G7: =RawFS!I39 -> 36089 | H7: =RawFS!J39 -> 35240
B8: =RawFS!B40 -> Trade receivables | D8: =RawFS!F40 -> 19893 | E8: =RawFS!G40 -> 18996 | F8: =RawFS!H40 -> 11173 | G8: =RawFS!I40 -> 12679 | H8: =RawFS!J40 -> 12442
B9: =RawFS!B42 -> Loans n Advances | D9: =RawFS!F42 -> 4066 | E9: =RawFS!G42 -> 3620 | F9: =RawFS!H42 -> 3353 | G9: =RawFS!I42 -> 4520 | H9: =RawFS!J42 -> 4583
B10: =RawFS!B43 -> Other asset items | D10: =RawFS!F43 -> 44221 | E10: =RawFS!G43 -> 52535 | F10: =RawFS!H43 -> 55432 | G10: =RawFS!I43 -> 57198 | H10: =RawFS!J43 -> 57641
B11: Total Current assest | D11: =SUM(D7:D10) -> 110318 | E11: =SUM(E7:E10) -> 114165 | F11: =SUM(F7:F10) -> 107415 | G11: =SUM(G7:G10) -> 110486 | H11: =SUM(H7:H10) -> 109906
B13: Current Liabilities
B14: =RawFS!B20 -> Trade Payables | D14: =RawFS!F20 -> 76940 | E14: =RawFS!G20 -> 71691 | F14: =RawFS!H20 -> 66398 | G14: =RawFS!I20 -> 76040 | H14: =RawFS!J20 -> 69750
B15: =RawFS!B21 -> Advance from Customers | D15: =RawFS!F21 -> 0 | E15: =RawFS!G21 -> 0 | F15: =RawFS!H21 -> 0 | G15: =RawFS!I21 -> 0 | H15: =RawFS!J21 -> 0
B16: =RawFS!B22 -> Other liability items | D16: =RawFS!F22 -> 65349 | E16: =RawFS!G22 -> 67135 | F16: =RawFS!H22 -> 65101 | G16: =RawFS!I22 -> 66579 | H16: =RawFS!J22 -> 64030
B17: Total Current Liabilites | D17: =SUM(D14:D16) -> 142289 | E17: =SUM(E14:E16) -> 138826 | F17: =SUM(F14:F16) -> 131499 | G17: =SUM(G14:G16) -> 142619 | H17: =SUM(H14:H16) -> 133780
B19: Net Working Capital | D19: =D11-D17 -> -31971 | E19: =E11-E17 -> -24661 | F19: =F11-F17 -> -24084 | G19: =G11-G17 -> -32133 | H19: =H11-H17 -> -23874
B22: Non Current Assets
B23: =RawFS!B25 -> Land | D23: =RawFS!F25 -> 7339 | E23: =RawFS!G25 -> 7286 | F23: =RawFS!H25 -> 7675 | G23: =RawFS!I25 -> 7819 | H23: =RawFS!J25 -> 7760
B24: =RawFS!B26 -> Building | D24: =RawFS!F26 -> 16552 | E24: =RawFS!G26 -> 22938 | F24: =RawFS!H26 -> 32665 | G24: =RawFS!I26 -> 35537 | H24: =RawFS!J26 -> 36466
B25: =RawFS!B27 -> Plant Machinery | D25: =RawFS!F27 -> 100226 | E25: =RawFS!G27 -> 109415 | F25: =RawFS!H27 -> 124158 | G25: =RawFS!I27 -> 138868 | H25: =RawFS!J27 -> 148585
B26: =RawFS!B28 -> Equipments | D26: =RawFS!F28 -> 0 | E26: =RawFS!G28 -> 0 | F26: =RawFS!H28 -> 0 | G26: =RawFS!I28 -> 0 | H26: =RawFS!J28 -> 0
B27: =RawFS!B29 -> Computers | D27: =RawFS!F29 -> 1943 | E27: =RawFS!G29 -> 2335 | F27: =RawFS!H29 -> 3054 | G27: =RawFS!I29 -> 3172 | H27: =RawFS!J29 -> 3383
B28: =RawFS!B30 -> Furniture n fittings | D28: =RawFS!F30 -> 1430 | E28: =RawFS!G30 -> 1626 | F28: =RawFS!H30 -> 1890 | G28: =RawFS!I30 -> 1956 | H28: =RawFS!J30 -> 1984
B29: =RawFS!B31 -> Vehicles | D29: =RawFS!F31 -> 353 | E29: =RawFS!G31 -> 387 | F29: =RawFS!H31 -> 601 | G29: =RawFS!I31 -> 845 | H29: =RawFS!J31 -> 725
B30: =RawFS!B32 -> Intangible Assets | D30: =RawFS!F32 -> 77870 | E30: =RawFS!G32 -> 80480 | F30: =RawFS!H32 -> 91157 | G30: =RawFS!I32 -> 114809 | H30: =RawFS!J32 -> 114323
B31: =RawFS!B33 -> Other fixed assets | D31: =RawFS!F33 -> 7497 | E31: =RawFS!G33 -> 8049 | F31: =RawFS!H33 -> 9380 | G31: =RawFS!I33 -> 10686 | H31: =RawFS!J33 -> 10870
B33: Gross Block | D33: =SUM(D23:D31) -> 213210 | E33: =SUM(E23:E31) -> 232516 | F33: =SUM(F23:F31) -> 270580 | G33: =SUM(G23:G31) -> 313692 | H33: =SUM(H23:H31) -> 324096
B34: Accumulated Depreciation | D34: =-RawFS!F35 -> -91795 | E34: =-RawFS!G35 -> -121283 | F34: =-RawFS!H35 -> -143471 | G34: =-RawFS!I35 -> -174985 | H34: =-RawFS!J35 -> -185241
B35: Net Non Current Assets | D35: =SUM(D33:D34) -> 121415 | E35: =SUM(E33:E34) -> 111233 | F35: =SUM(F33:F34) -> 127109 | G35: =SUM(G33:G34) -> 138707 | H35: =SUM(H33:H34) -> 138855
B37: Invested capital | D37: =D35+D19 -> 89444 | E37: =E35+E19 -> 86572 | F37: =F35+F19 -> 103025 | G37: =G35+G19 -> 106574 | H37: =H35+H19 -> 114981
B38: EBIT | D38: ='Historical Data'!H25+'Historical Data'!H19 -> 9904.09 | E38: ='Historical Data'!I25+'Historical Data'!I19 -> 1073.7 | F38: ='Historical Data'!J25+'Historical Data'!J19 -> -3438.36 | G38: ='Historical Data'!K25+'Historical Data'!K19 -> 8740.72 | H38: ='Historical Data'!L25+'Historical Data'!L19 -> -115.6
B40: ROIC | D40: =D38/D37 -> 0.11072951 | E40: =E38/E37 -> 0.012402393 | F40: =F38/F37 -> -0.033374035 | G40: =G38/G37 -> 0.082015501 | H40: =H38/H37 -> -0.0010053835
B43: Calculation of Reinvestment Rate | D43: =D4 -> 43160 | E43: =E4 -> 43525 | F43: =F4 -> 43891 | G43: =G4 -> 44256 | H43: =H4 -> 44621
B45: Net Captial Expenditure | D45: =SUM(RawFS!F58,RawFS!F59) -> -35049 | E45: =SUM(RawFS!G58,RawFS!G59) -> -35237 | F45: =SUM(RawFS!H58,RawFS!H59) -> -29531 | G45: =SUM(RawFS!I58,RawFS!I59) -> -19854 | H45: =SUM(RawFS!J58,RawFS!J59) -> -14938
B46: Change in Working Capital | E46: =E19-D19 -> 7310 | F46: =F19-E19 -> 577 | G46: =G19-F19 -> -8049 | H46: =H19-G19 -> 8259
B48: EBIT | D48: =D38 -> 9904.09 | E48: =E38 -> 1073.7 | F48: =F38 -> -3438.36 | G48: =G38 -> 8740.72 | H48: =H38 -> -115.6
B49: Marginal Tax Rate | D49: 0.25 | E49: 0.25 | F49: 0.25 | G49: 0.25 | H49: 0.25
B50: EBIT(1-T) | D50: =D48*(1-D49) -> 7428.0675 | E50: =E48*(1-E49) -> 805.275 | F50: =F48*(1-F49) -> -2578.77 | G50: =G48*(1-G49) -> 6555.54 | H50: =H48*(1-H49) -> -86.7
B52: Reinvestment | E52: =SUM(E45:E46) -> -27927 | F52: =SUM(F45:F46) -> -28954 | G52: =SUM(G45:G46) -> -27903 | H52: =SUM(H45:H46) -> -6679
B53: Reinvestment Rate | E53: =E52/E50 -> -34.680078 | F53: =F52/F50 -> 11.227833 | G53: =G52/G50 -> -4.2563999 | H53: =H52/H50 -> 77.035755
G55: 4-year Average | H55: =AVERAGE(E53:H53) -> 12.331778
G56: 4-year Median | H56: =MEDIAN(E53:H53) -> 3.4857167
B58: Calculation of Growth rate | D58: =D43 -> 43160 | E58: =E43 -> 43525 | F58: =F43 -> 43891 | G58: =G43 -> 44256 | H58: =H43 -> 44621
B60: Reinvestment rate | E60: =E53 -> -34.680078 | F60: =F53 -> 11.227833 | G60: =G53 -> -4.2563999 | H60: =H53 -> 77.035755
B61: ROIC | E61: =E40 -> 0.012402393 | F61: =F40 -> -0.033374035 | G61: =G40 -> 0.082015501 | H61: =H40 -> -0.0010053835
B63: Intrinsic Growth Rate | E63: =E60*E61 -> -0.43011597 | F63: =F60*F61 -> -0.37471811 | G63: =G60*G61 -> -0.34909077 | H63: =H60*H61 -> -0.077450477
G65: 4-year Average | H65: =AVERAGE(E63:H63) -> -0.30784383
G66: 4-year Median | H66: =MEDIAN(E63:H63) -> -0.36190444

Sheet DCF
B3: Calculation of PV of FCFF | D3: ='Intrinsic growth'!H43 -> 44621 | E3: =D3+366 -> 44987 | F3: =E3+366 -> 45353 | G3: =F3+366 -> 45719 | H3: =G3+366 -> 46085 | I3: =H3+366 -> 46451
B5: EBIT | D5: ='Data Sheet'!I51-'Data Sheet'!I45 -> 2105.9 | E5: =D5*(1+$D$21) -> 2542.8743 | F5: =E5*(1+$D$21) -> 3070.5207 | G5: =F5*(1+$D$21) -> 3707.6537 | H5: =G5*(1+$D$21) -> 4476.9918 | I5: =H5*(1+$D$21) -> 5405.9676
B7: Tax rate | D7: 0.25 | E7: =D7 -> 0.25 | F7: =E7 -> 0.25 | G7: =F7 -> 0.25 | H7: =G7 -> 0.25 | I7: =H7 -> 0.25
B9: EBIT(1-T) | D9: =D5*(1-D7) -> 1579.425 | E9: =E5*(1-E7) -> 1907.1557 | F9: =F5*(1-F7) -> 2302.8905 | G9: =G5*(1-G7) -> 2780.7403 | H9: =H5*(1-H7) -> 3357.7439 | I9: =I5*(1-I7) -> 4054.4757
B11: Less: Reinvestment rate | D11: ='Intrinsic growth'!H56 -> 3.4857167 | E11: =D11-((D11-I11)/4) -> 2.8280376 | F11: =E11-((E11-J11)/4) -> 2.1210282 | G11: =F11-((F11-K11)/4) -> 1.5907711 | H11: =G11-((G11-L11)/4) -> 1.1930783 | I11: 0.855
B13: Free Cash Flow to Firm (FCFF) | D13: =D9*(1-D11) -> -3926.0032 | E13: =E9*(1-E11) -> -3486.3522 | F13: =F9*(1-F11) -> -2581.6051 | G13: =G9*(1-G11) -> -1642.7811 | H13: =H9*(1-H11) -> -648.30763 | I13: =I9*(1-I11) -> 587.89898
B15: Mid Year Convention | E15: 0.5 | F15: =E15+1 -> 1.5 | G15: =F15+1 -> 2.5 | H15: =G15+1 -> 3.5 | I15: =H15+1 -> 4.5
B16: Discounting factor | E16: =1/(1+$D$23)^E15 -> 0.93368941 | F16: =1/(1+$D$23)^F15 -> 0.81396793 | G16: =1/(1+$D$23)^G15 -> 0.70959763 | H16: =1/(1+$D$23)^H15 -> 0.61861012 | I16: =1/(1+$D$23)^I15 -> 0.5392894
B18: PV of FCFF | E18: =E13*E16 -> -3255.1701 | F18: =F13*F16 -> -2101.3438 | G18: =G13*G16 -> -1165.7136 | H18: =H13*H16 -> -401.04966 | I18: =I13*I16 -> 317.04769
B21: Expected Growth | D21: 0.2075
B22: Terminal Growth | D22: 0.0538
B23: WACC | D23: =WACC!L39 -> 0.14708378
B26: Calculation of Terminal Value
B28: FCFF(n+1) | C28: =I13*(1+D21) -> 709.88802
B29: WACC | C29: =D23 -> 0.14708378
B30: Terminal Growth Rate | C30: =D22 -> 0.0538
B32: Terminal Value | C32: =C28/(C29-C30) -> 7609.9838
B35: Calculation of Equity Value
B37: PV of FCFF | C37: =SUM(E18:I18) -> -6606.2294
B38: PV of Terminal value | C38: =C32*I16 -> 4103.9836
B39: Value of Operating Assests(EV) | C39: =SUM(C37:C38) -> -2502.2459
B41: Add:Cash | C41: ='Data Sheet'!K69 -> 40669.19
B42: Less:Debt | C42: =SUM(RawFS!J14:J15) -> 139677
B43: Equity Value | C43: =C39+C41-C42 -> -101510.06
B44: No of shares | C44: ='Data Sheet'!B6 -> 358.58909
B45: Equity value per share | C45: =C43/C44 -> -283.08183
B48: Share price | C48: 473.6
B49: Discount/Premium | C49: =C48/C45 -> -1.6730145

Sheet Financials>

Sheet Historical Data
B2: ="Historical Financial Statement"&"-"&'Data Sheet'!B1 -> Historical Financial Statement-TATA MOTORS LTD
B3: Years | C3: ='Data Sheet'!B16 -> 41364 | D3: ='Data Sheet'!C16 -> 41729 | E3: ='Data Sheet'!D16 -> 42094 | F3: ='Data Sheet'!E16 -> 42460 | G3: ='Data Sheet'!F16 -> 42825 | H3: ='Data Sheet'!G16 -> 43190 | I3: ='Data Sheet'!H16 -> 43555 | J3: ='Data Sheet'!I16 -> 43921 | ... L3: ='Data Sheet'!K16 -> 44651 | M3: LTM
A4: # | B4: Income Statement
B5: Sales | C5: =IFERROR('Data Sheet'!B17,0) -> 188792.69 | D5: =IFERROR('Data Sheet'!C17,0) -> 232833.66 | E5: =IFERROR('Data Sheet'!D17,0) -> 263158.98 | F5: =IFERROR('Data Sheet'!E17,0) -> 273045.6 | G5: =IFERROR('Data Sheet'!F17,0) -> 269692.51 | H5: =IFERROR('Data Sheet'!G17,0) -> 291550.48 | I5: =IFERROR('Data Sheet'!H17,0) -> 301938.4 | J5: =IFERROR('Data Sheet'!I17,0) -> 261067.97 | ... L5: =IFERROR('Data Sheet'!K17,0) -> 278453.62 | M5: =IFERROR(SUM('Data Sheet'!H42:K42),0) -> 302214.38
B6: Sales Growth | C6: - | D6: =D5/C5-1 -> 0.23327688 | E6: =E5/D5-1 -> 0.13024457 | F6: =F5/E5-1 -> 0.037569001 | G6: =G5/F5-1 -> -0.01228033 | H6: =H5/G5-1 -> 0.081047746 | I6: =I5/H5-1 -> 0.035629919 | J6: =J5/I5-1 -> -0.13536016 | K6: =K5/J5-1 -> -0.043181168 | ... M6: =M5/L5-1 -> 0.085331123
B8: COGS | C8: =IFERROR((SUM('Data Sheet'!B18,'Data Sheet'!B20,'Data Sheet'!B21,'Data Sheet'!B22)-1*'Data Sheet'!B19),0) -> 142238.74 | D8: =IFERROR((SUM('Data Sheet'!C18,'Data Sheet'!C20,'Data Sheet'!C21,'Data Sheet'!C22)-1*'Data Sheet'!C19),0) -> 180131.06 | E8: =IFERROR((SUM('Data Sheet'!D18,'Data Sheet'!D20,'Data Sheet'!D21,'Data Sheet'!D22)-1*'Data Sheet'!D19),0) -> 202856.88 | F8: =IFERROR((SUM('Data Sheet'!E18,'Data Sheet'!E20,'Data Sheet'!E21,'Data Sheet'!E22)-1*'Data Sheet'!E19),0) -> 205509.07 | G8: =IFERROR((SUM('Data Sheet'!F18,'Data Sheet'!F20,'Data Sheet'!F21,'Data Sheet'!F22)-1*'Data Sheet'!F19),0) -> 205454.24 | H8: =IFERROR((SUM('Data Sheet'!G18,'Data Sheet'!G20,'Data Sheet'!G21,'Data Sheet'!G22)-1*'Data Sheet'!G19),0) -> 228429.83 | I8: =IFERROR((SUM('Data Sheet'!H18,'Data Sheet'!H20,'Data Sheet'!H21,'Data Sheet'!H22)-1*'Data Sheet'!H19),0) -> 242845.53 | J8: =IFERROR((SUM('Data Sheet'!I18,'Data Sheet'!I20,'Data Sheet'!I21,'Data Sheet'!I22)-1*'Data Sheet'!I19),0) -> 210376.07 | ... L8: =IFERROR((SUM('Data Sheet'!K18,'Data Sheet'!K20,'Data Sheet'!K21,'Data Sheet'!K22)-1*'Data Sheet'!K19),0) -> 223300.01 | M8: =IFERROR(SUM('Data Sheet'!H43:K43),0) -> 278868.53
B9: COGS % Sales | C9: =C8/C5 -> 0.75341233 | D9: =D8/D5 -> 0.77364699 | E9: =E8/E5 -> 0.77085297 | F9: =F8/F5 -> 0.75265476 | G9: =G8/G5 -> 0.76180922 | H9: =H8/H5 -> 0.7835001 | I9: =I8/I5 -> 0.80428833 | J9: =J8/J5 -> 0.80582873 | ... M9: =M8/M5 -> 0.9227507
B11: Gross Profit | C11: =C5-C8 -> 46553.95 | D11: =D5-D8 -> 52702.6 | E11: =E5-E8 -> 60302.1 | F11: =F5-F8 -> 67536.53 | G11: =G5-G8 -> 64238.27 | H11: =H5-H8 -> 63120.65 | I11: =I5-I8 -> 59092.87 | J11: =J5-J8 -> 50691.9 | ... M11: =M5-M8 -> 23345.85
B13: Selling and General expenses | C13: =IFERROR(SUM('Data Sheet'!B23:B24),0) -> 21957.97 | D13: =IFERROR(SUM('Data Sheet'!C23:C24),0) -> 17849.24 | E13: =IFERROR(SUM('Data Sheet'!D23:D24),0) -> 21063.45 | F13: =IFERROR(SUM('Data Sheet'!E23:E24),0) -> 29141.28 | G13: =IFERROR(SUM('Data Sheet'!F23:F24),0) -> 34649.58 | H13: =IFERROR(SUM('Data Sheet'!G23:G24),0) -> 31662.97 | I13: =IFERROR(SUM('Data Sheet'!H23:H24),0) -> 34428.54 | J13: =IFERROR(SUM('Data Sheet'!I23:I24),0) -> 32704.83 | ... M13: =IFERROR(SUM('Data Sheet'!L23:L24),0) -> 0
B14: S&G Expenses % Sales | C14: =C13/C5 -> 0.11630731 | D14: =D13/D5 -> 0.076660909 | E14: =E13/E5 -> 0.08004078 | F14: =F13/F5 -> 0.10672679 | G14: =G13/G5 -> 0.1284781 | H14: =H13/H5 -> 0.10860202 | I14: =I13/I5 -> 0.11402505 | J14: =J13/J5 -> 0.12527324 | ... M14: =M13/M5 -> 0
B16: EBITDA | C16: =C11-C13 -> 24595.98 | D16: =D11-D13 -> 34853.36 | E16: =E11-E13 -> 39238.65 | F16: =F11-F13 -> 38395.25 | G16: =G11-G13 -> 29588.69 | H16: =H11-H13 -> 31457.68 | I16: =I11-I13 -> 24664.33 | J16: =J11-J13 -> 17987.07 | ... L16: =L11-L13 -> 24720.09 | M16: =IFERROR(SUM('Data Sheet'!H51:K51),0) -> 27983.82
B17: EBITDA % Sales | C17: =C16/C5 -> 0.13028036 | D17: =D16/D5 -> 0.1496921 | E17: =E16/E5 -> 0.14910626 | F17: =F16/F5 -> 0.14061845 | G17: =G16/G5 -> 0.10971269 | H17: =H16/H5 -> 0.10789788 | I17: =I16/I5 -> 0.081686629 | J17: =J16/J5 -> 0.068898034 | ... M17: =M16/M5 -> 0.092595925
B19: Interest | C19: =IFERROR('Data Sheet'!B27,0) -> 3560.25 | D19: =IFERROR('Data Sheet'!C27,0) -> 4749.44 | E19: =IFERROR('Data Sheet'!D27,0) -> 4861.49 | F19: =IFERROR('Data Sheet'!E27,0) -> 4889.08 | G19: =IFERROR('Data Sheet'!F27,0) -> 4238.01 | H19: =IFERROR('Data Sheet'!G27,0) -> 4681.79 | I19: =IFERROR('Data Sheet'!H27,0) -> 5758.6 | J19: =IFERROR('Data Sheet'!I27,0) -> 7243.33 | ... L19: =IFERROR('Data Sheet'!K27,0) -> 9311.86 | M19: =IFERROR(SUM('Data Sheet'!H46:K46),0) -> 9689.24
B20: Interest % Sales | C20: =C19/C5 -> 0.018857987 | D20: =D19/D5 -> 0.020398425 | E20: =E19/E5 -> 0.018473586 | F20: =F19/F5 -> 0.017905727 | G20: =G19/G5 -> 0.01571423 | H20: =H19/H5 -> 0.016058248 | I20: =I19/I5 -> 0.019072102 | J20: =J19/J5 -> 0.027744997 | ... M20: =M19/M5 -> 0.032060817
B22: Depreciation | C22: =IFERROR('Data Sheet'!B26,0) -> 7601.28 | D22: =IFERROR('Data Sheet'!C26,0) -> 11078.16 | E22: =IFERROR('Data Sheet'!D26,0) -> 13388.63 | F22: =IFERROR('Data Sheet'!E26,0) -> 16710.78 | G22: =IFERROR('Data Sheet'!F26,0) -> 17904.99 | H22: =IFERROR('Data Sheet'!G26,0) -> 21553.59 | I22: =IFERROR('Data Sheet'!H26,0) -> 23590.63 | J22: =IFERROR('Data Sheet'!I26,0) -> 21425.43 | ... L22: =IFERROR('Data Sheet'!K26,0) -> 24835.69 | M22: =IFERROR(SUM('Data Sheet'!H45:K45),0) -> 24248.62
B23: Depreciation % Sales | C23: =C22/C5 -> 0.040262576 | D23: =D22/D5 -> 0.047579718 | E23: =E22/E5 -> 0.050876584 | F23: =F22/F5 -> 0.061201426 | G23: =G22/G5 -> 0.066390387 | H23: =H22/H5 -> 0.073927472 | I23: =I22/I5 -> 0.078130605 | J23: =J22/J5 -> 0.082068398 | ... M23: =M22/M5 -> 0.080236486
B25: EBT | C25: =IFERROR(C16-SUM(C19,C22),0) -> 13434.45 | D25: =IFERROR(D16-SUM(D19,D22),0) -> 19025.76 | E25: =IFERROR(E16-SUM(E19,E22),0) -> 20988.53 | F25: =IFERROR(F16-SUM(F19,F22),0) -> 16795.39 | G25: =IFERROR(G16-SUM(G19,G22),0) -> 7445.69 | H25: =IFERROR(H16-SUM(H19,H22),0) -> 5222.3 | I25: =IFERROR(I16-SUM(I19,I22),0) -> -4684.9 | J25: =IFERROR(J16-SUM(J19,J22),0) -> -10681.69 | ... M25: =IFERROR(M16-SUM(M19,M22),0) -> -5954.04
B26: EBT % sales | C26: =C25/C5 -> 0.0711598 | D26: =D25/D5 -> 0.081713958 | E26: =E25/E5 -> 0.079756085 | F26: =F25/F5 -> 0.061511301 | G26: =G25/G5 -> 0.027608071 | H26: =H25/H5 -> 0.017912164 | I26: =I25/I5 -> -0.015516079 | J26: =J25/J5 -> -0.04091536 | ... M26: =M25/M5 -> -0.019701379
B28: Taxes | C28: =IFERROR('Data Sheet'!B29,0) -> 3776.66 | D28: =IFERROR('Data Sheet'!C29,0) -> 4764.79 | E28: =IFERROR('Data Sheet'!D29,0) -> 7642.91 | F28: =IFERROR('Data Sheet'!E29,0) -> 3025.05 | G28: =IFERROR('Data Sheet'!F29,0) -> 3251.23 | H28: =IFERROR('Data Sheet'!G29,0) -> 4341.93 | I28: =IFERROR('Data Sheet'!H29,0) -> -2437.45 | J28: =IFERROR('Data Sheet'!I29,0) -> 395.25 | ... L28: =IFERROR('Data Sheet'!K29,0) -> 4231.29 | M28: =IFERROR(SUM('Data Sheet'!H48:K48),0) -> 2546.15
B29: Effective Tax rate | C29: =C28/C25 -> 0.28111757 | D29: =D28/D25 -> 0.25043888 | E29: =E28/E25 -> 0.36414699 | F29: =F28/F25 -> 0.18011192 | G29: =G28/G25 -> 0.43665933 | H29: =H28/H25 -> 0.83142102 | I29: =I28/I25 -> 0.52027791 | J29: =J28/J25 -> -0.037002572 | ... M29: =M28/M25 -> -0.42763401
B31: Net Profit | C31: =C25-C28 -> 9657.79 | D31: =D25-D28 -> 14260.97 | E31: =E25-E28 -> 13345.62 | F31: =F25-F28 -> 13770.34 | G31: =G25-G28 -> 4194.46 | H31: =H25-H28 -> 880.37 | I31: =I25-I28 -> -2247.45 | J31: =J25-J28 -> -11076.94 | ... M31: =M25-M28 -> -8500.19
B32: Net Profit % Sales | C32: =C31/C5 -> 0.051155529 | D32: =D31/D5 -> 0.061249606 | E32: =E31/E5 -> 0.050713147 | F32: =F31/F5 -> 0.050432382 | G32: =G31/G5 -> 0.015552749 | H32: =H31/H5 -> 0.0030196143 | I32: =I31/I5 -> -0.0074434057 | J32: =J31/J5 -> -0.042429334 | ... M32: =M31/M5 -> -0.028126359
B34: No of Equity shares | C34: =IFERROR('Data Sheet'!B93,0) -> 285.72 | D34: =IFERROR('Data Sheet'!C93,0) -> 288.74 | E34: =IFERROR('Data Sheet'!D93,0) -> 288.74 | F34: =IFERROR('Data Sheet'!E93,0) -> 288.72 | G34: =IFERROR('Data Sheet'!F93,0) -> 288.73 | H34: =IFERROR('Data Sheet'!G93,0) -> 288.73 | I34: =IFERROR('Data Sheet'!H93,0) -> 288.73 | J34: =IFERROR('Data Sheet'!I93,0) -> 308.9 | ... L34: =IFERROR('Data Sheet'!K93,0) -> 332.07 | M34: -
B36: EPS | C36: =IFERROR(C31/C34,0) -> 33.801589 | D36: =IFERROR(D31/D34,0) -> 49.390351 | E36: =IFERROR(E31/E34,0) -> 46.220198 | F36: =IFERROR(F31/F34,0) -> 47.694444 | G36: =IFERROR(G31/G34,0) -> 14.527275 | H36: =IFERROR(H31/H34,0) -> 3.0491116 | I36: =IFERROR(I31/I34,0) -> -7.7839158 | J36: =IFERROR(J31/J34,0) -> -35.859307 | ... M36: =IFERROR(M31/M34,0) -> 0
B37: EPS Growth % | D37: =D36/C36-1 -> 0.4611843 | E37: =E36/D36-1 -> -0.064185676 | F37: =F36/E36-1 -> 0.031896149 | G37: =G36/F36-1 -> -0.6954095 | H37: =H36/G36-1 -> -0.79011124 | I37: =I36/H36-1 -> -3.5528471 | J37: =J36/I36-1 -> 3.6068468 | K37: =K36/J36-1 -> -0.84056344 | ... M37: =M36/L36-1 -> -1
B39: Dividends per Share | C39: =IFERROR('Data Sheet'!B31/'Historical Data'!C34,0) -> 2.2332003 | D39: =IFERROR('Data Sheet'!C31/'Historical Data'!D34,0) -> 2.2296183 | E39: =IFERROR('Data Sheet'!D31/'Historical Data'!E34,0) -> 0 | F39: =IFERROR('Data Sheet'!E31/'Historical Data'!F34,0) -> 0.23524522 | G39: =IFERROR('Data Sheet'!F31/'Historical Data'!G34,0) -> 0 | H39: =IFERROR('Data Sheet'!G31/'Historical Data'!H34,0) -> 0 | I39: =IFERROR('Data Sheet'!H31/'Historical Data'!I34,0) -> 0 | J39: =IFERROR('Data Sheet'!I31/'Historical Data'!J34,0) -> 0 | ... M39: =IFERROR('Data Sheet'!L31/'Historical Data'!M34,0) -> 0
B40: Dividend payout ratio | C40: =IFERROR(C39/C36,0) -> 0.06606791 | D40: =IFERROR(D39/D36,0) -> 0.045142792 | E40: =IFERROR(E39/E36,0) -> 0 | F40: =IFERROR(F39/F36,0) -> 0.0049323401 | G40: =IFERROR(G39/G36,0) -> 0 | H40: =IFERROR(H39/H36,0) -> 0 | I40: =IFERROR(I39/I36,0) -> 0 | J40: =IFERROR(J39/J36,0) -> 0 | ... M40: =IFERROR(M39/M36,0) -> 0
B42: Retained Earnings | C42: =IFERROR(IF(C36>C39,1-C40,0),0) -> 0.93393209 | D42: =IFERROR(IF(D36>D39,1-D40,0),0) -> 0.95485721 | E42: =IFERROR(IF(E36>E39,1-E40,0),0) -> 1 | F42: =IFERROR(IF(F36>F39,1-F40,0),0) -> 0.99506766 | G42: =IFERROR(IF(G36>G39,1-G40,0),0) -> 1 | H42: =IFERROR(IF(H36>H39,1-H40,0),0) -> 1 | I42: =IFERROR(IF(I36>I39,1-I40,0),0) -> 0 | J42: =IFERROR(IF(J36>J39,1-J40,0),0) -> 0 | ... M42: =IFERROR(IF(M36>M39,1-M40,0),0) -> 0
A44: # | B44: Balance Sheet
B46: Equity Share Capital | C46: =IFERROR('Data Sheet'!B57,0) -> 638.07 | D46: =IFERROR('Data Sheet'!C57,0) -> 643.78 | E46: =IFERROR('Data Sheet'!D57,0) -> 643.78 | F46: =IFERROR('Data Sheet'!E57,0) -> 679.18 | G46: =IFERROR('Data Sheet'!F57,0) -> 679.22 | H46: =IFERROR('Data Sheet'!G57,0) -> 679.22 | I46: =IFERROR('Data Sheet'!H57,0) -> 679.22 | J46: =IFERROR('Data Sheet'!I57,0) -> 719.54 | ... L46: =IFERROR('Data Sheet'!K57,0) -> 765.88
B47: Reserves | C47: =IFERROR('Data Sheet'!B58,0) -> 36999.23 | D47: =IFERROR('Data Sheet'!C58,0) -> 64959.67 | E47: =IFERROR('Data Sheet'!D58,0) -> 55618.14 | F47: =IFERROR('Data Sheet'!E58,0) -> 78273.23 | G47: =IFERROR('Data Sheet'!F58,0) -> 57382.67 | H47: =IFERROR('Data Sheet'!G58,0) -> 94748.69 | I47: =IFERROR('Data Sheet'!H58,0) -> 59500.34 | J47: =IFERROR('Data Sheet'!I58,0) -> 61491.49 | ... L47: =IFERROR('Data Sheet'!K58,0) -> 43795.36
B48: Borrowings | C48: =IFERROR('Data Sheet'!B59,0) -> 53715.71 | D48: =IFERROR('Data Sheet'!C59,0) -> 60642.28 | E48: =IFERROR('Data Sheet'!D59,0) -> 73610.39 | F48: =IFERROR('Data Sheet'!E59,0) -> 69359.96 | G48: =IFERROR('Data Sheet'!F59,0) -> 78603.98 | H48: =IFERROR('Data Sheet'!G59,0) -> 88950.47 | I48: =IFERROR('Data Sheet'!H59,0) -> 106175.34 | J48: =IFERROR('Data Sheet'!I59,0) -> 124787.64 | ... L48: =IFERROR('Data Sheet'!K59,0) -> 146449.03
B49: Other Liabilities | C49: =IFERROR('Data Sheet'!B60,0) -> 76977.02 | D49: =IFERROR('Data Sheet'!C60,0) -> 92180.26 | E49: =IFERROR('Data Sheet'!D60,0) -> 107442.48 | F49: =IFERROR('Data Sheet'!E60,0) -> 114871.75 | G49: =IFERROR('Data Sheet'!F60,0) -> 135914.49 | H49: =IFERROR('Data Sheet'!G60,0) -> 142813.43 | I49: =IFERROR('Data Sheet'!H60,0) -> 139348.59 | J49: =IFERROR('Data Sheet'!I60,0) -> 133180.72 | ... L49: =IFERROR('Data Sheet'!K60,0) -> 138051.22
B50: Total Liabilities | C50: =IFERROR('Data Sheet'!B61,0) -> 168330.03 | D50: =IFERROR('Data Sheet'!C61,0) -> 218425.99 | E50: =IFERROR('Data Sheet'!D61,0) -> 237314.79 | F50: =IFERROR('Data Sheet'!E61,0) -> 263184.12 | G50: =IFERROR('Data Sheet'!F61,0) -> 272580.36 | H50: =IFERROR('Data Sheet'!G61,0) -> 327191.81 | I50: =IFERROR('Data Sheet'!H61,0) -> 305703.49 | J50: =IFERROR('Data Sheet'!I61,0) -> 320179.39 | ... L50: =IFERROR('Data Sheet'!K61,0) -> 329061.49
B52: Total assests Net Block | C52: =IFERROR('Data Sheet'!B62,0) -> 55511.73 | D52: =IFERROR('Data Sheet'!C62,0) -> 69091.67 | E52: =IFERROR('Data Sheet'!D62,0) -> 88479.49 | F52: =IFERROR('Data Sheet'!E62,0) -> 107231.76 | G52: =IFERROR('Data Sheet'!F62,0) -> 95944.08 | H52: =IFERROR('Data Sheet'!G62,0) -> 121413.86 | I52: =IFERROR('Data Sheet'!H62,0) -> 111234.47 | J52: =IFERROR('Data Sheet'!I62,0) -> 127107.14 | ... L52: =IFERROR('Data Sheet'!K62,0) -> 138855.45
B53: Capital Work in Progress | C53: =IFERROR('Data Sheet'!B63,0) -> 18453.55 | D53: =IFERROR('Data Sheet'!C63,0) -> 33262.56 | E53: =IFERROR('Data Sheet'!D63,0) -> 28640.09 | F53: =IFERROR('Data Sheet'!E63,0) -> 25918.94 | G53: =IFERROR('Data Sheet'!F63,0) -> 33698.84 | H53: =IFERROR('Data Sheet'!G63,0) -> 40033.5 | I53: =IFERROR('Data Sheet'!H63,0) -> 31883.84 | J53: =IFERROR('Data Sheet'!I63,0) -> 35622.29 | ... L53: =IFERROR('Data Sheet'!K63,0) -> 10251.09
B54: Investments | C54: =IFERROR('Data Sheet'!B64,0) -> 8764.73 | D54: =IFERROR('Data Sheet'!C64,0) -> 10686.67 | E54: =IFERROR('Data Sheet'!D64,0) -> 15336.74 | F54: =IFERROR('Data Sheet'!E64,0) -> 23767.02 | G54: =IFERROR('Data Sheet'!F64,0) -> 20337.92 | H54: =IFERROR('Data Sheet'!G64,0) -> 20812.75 | I54: =IFERROR('Data Sheet'!H64,0) -> 15770.72 | J54: =IFERROR('Data Sheet'!I64,0) -> 16308.48 | ... L54: =IFERROR('Data Sheet'!K64,0) -> 29379.53
B55: Other Assets | C55: =IFERROR('Data Sheet'!B65-SUM('Data Sheet'!B67:B69),0) -> 32488.78 | D55: =IFERROR('Data Sheet'!C65-SUM('Data Sheet'!C67:C69),0) -> 37828.18 | E55: =IFERROR('Data Sheet'!D65-SUM('Data Sheet'!D67:D69),0) -> 30891.17 | F55: =IFERROR('Data Sheet'!E65-SUM('Data Sheet'!E67:E69),0) -> 29579.36 | G55: =IFERROR('Data Sheet'!F65-SUM('Data Sheet'!F67:F69),0) -> 37360.78 | H55: =IFERROR('Data Sheet'!G65-SUM('Data Sheet'!G67:G69),0) -> 48286.86 | I55: =IFERROR('Data Sheet'!H65-SUM('Data Sheet'!H67:H69),0) -> 56155.74 | J55: =IFERROR('Data Sheet'!I65-SUM('Data Sheet'!I67:I69),0) -> 58784.94 | ... L55: =IFERROR('Data Sheet'!K65-SUM('Data Sheet'!K67:K69),0) -> 62223.77
B56: Total non Current Assets | C56: =SUM(C52:C55) -> 115218.79 | D56: =SUM(D52:D55) -> 150869.08 | E56: =SUM(E52:E55) -> 163347.49 | F56: =SUM(F52:F55) -> 186497.08 | G56: =SUM(G52:G55) -> 187341.62 | H56: =SUM(H52:H55) -> 230546.97 | I56: =SUM(I52:I55) -> 215044.77 | J56: =SUM(J52:J55) -> 237822.85 | ... L56: =SUM(L52:L55) -> 240709.84
B58: Receivables | C58: =IFERROR('Data Sheet'!B67,0) -> 10959.6 | D58: =IFERROR('Data Sheet'!C67,0) -> 10574.23 | E58: =IFERROR('Data Sheet'!D67,0) -> 12579.2 | F58: =IFERROR('Data Sheet'!E67,0) -> 13570.91 | G58: =IFERROR('Data Sheet'!F67,0) -> 14075.55 | H58: =IFERROR('Data Sheet'!G67,0) -> 19893.3 | I58: =IFERROR('Data Sheet'!H67,0) -> 18996.17 | J58: =IFERROR('Data Sheet'!I67,0) -> 11172.69 | ... L58: =IFERROR('Data Sheet'!K67,0) -> 12442.12
B59: Inventory | C59: =IFERROR('Data Sheet'!B68,0) -> 21036.82 | D59: =IFERROR('Data Sheet'!C68,0) -> 27270.89 | E59: =IFERROR('Data Sheet'!D68,0) -> 29272.34 | F59: =IFERROR('Data Sheet'!E68,0) -> 32655.73 | G59: =IFERROR('Data Sheet'!F68,0) -> 35085.31 | H59: =IFERROR('Data Sheet'!G68,0) -> 42137.63 | I59: =IFERROR('Data Sheet'!H68,0) -> 39013.73 | J59: =IFERROR('Data Sheet'!I68,0) -> 37456.88 | ... L59: =IFERROR('Data Sheet'!K68,0) -> 35240.34
B60: Cash & Bank | C60: =IFERROR('Data Sheet'!B69,0) -> 21114.82 | D60: =IFERROR('Data Sheet'!C69,0) -> 29711.79 | E60: =IFERROR('Data Sheet'!D69,0) -> 32115.76 | F60: =IFERROR('Data Sheet'!E69,0) -> 30460.4 | G60: =IFERROR('Data Sheet'!F69,0) -> 36077.88 | H60: =IFERROR('Data Sheet'!G69,0) -> 34613.91 | I60: =IFERROR('Data Sheet'!H69,0) -> 32648.82 | J60: =IFERROR('Data Sheet'!I69,0) -> 33726.97 | ... L60: =IFERROR('Data Sheet'!K69,0) -> 40669.19
B61: Total Current Assests | C61: =SUM(C58:C60) -> 53111.24 | D61: =SUM(D58:D60) -> 67556.91 | E61: =SUM(E58:E60) -> 73967.3 | F61: =SUM(F58:F60) -> 76687.04 | G61: =SUM(G58:G60) -> 85238.74 | H61: =SUM(H58:H60) -> 96644.84 | I61: =SUM(I58:I60) -> 90658.72 | J61: =SUM(J58:J60) -> 82356.54 | ... L61: =SUM(L58:L60) -> 88351.65
B63: Total Assests | C63: =C61+C56 -> 168330.03 | D63: =D61+D56 -> 218425.99 | E63: =E61+E56 -> 237314.79 | F63: =F61+F56 -> 263184.12 | G63: =G61+G56 -> 272580.36 | H63: =H61+H56 -> 327191.81 | I63: =I61+I56 -> 305703.49 | J63: =J61+J56 -> 320179.39 | ... L63: =L61+L56 -> 329061.49
B65: Check | C65: =C63=C50 -> TRUE | D65: =D63=D50 -> TRUE | E65: =E63=E50 -> TRUE | F65: =F63=F50 -> TRUE | G65: =G63=G50 -> TRUE | H65: =H63=H50 -> TRUE | I65: =I63=I50 -> TRUE | J65: =J63=J50 -> TRUE | ... L65: =L63=L50 -> TRUE
A67: # | B67: Cash Flow Statements
B68: Operating Activity
B69: Profit from operations | C69: =IFERROR('Cash Flow Data'!E4,0) -> 24406 | D69: =IFERROR('Cash Flow Data'!F4,0) -> 36303 | E69: =IFERROR('Cash Flow Data'!G4,0) -> 43397 | F69: =IFERROR('Cash Flow Data'!H4,0) -> 38626 | G69: =IFERROR('Cash Flow Data'!I4,0) -> 28840 | H69: =IFERROR('Cash Flow Data'!J4,0) -> 33312 | I69: =IFERROR('Cash Flow Data'!K4,0) -> 28771 | J69: =IFERROR('Cash Flow Data'!L4,0) -> 23352 | ... L69: =IFERROR('Cash Flow Data'!N4,0) -> 26666
B70: Receivables | C70: =IFERROR('Cash Flow Data'!E5,0) -> -5177 | D70: =IFERROR('Cash Flow Data'!F5,0) -> 445 | E70: =IFERROR('Cash Flow Data'!G5,0) -> -3179 | F70: =IFERROR('Cash Flow Data'!H5,0) -> -2223 | G70: =IFERROR('Cash Flow Data'!I5,0) -> -4152 | H70: =IFERROR('Cash Flow Data'!J5,0) -> -10688 | I70: =IFERROR('Cash Flow Data'!K5,0) -> -9109 | J70: =IFERROR('Cash Flow Data'!L5,0) -> 9950 | ... L70: =IFERROR('Cash Flow Data'!N5,0) -> 337
B71: Inventory | C71: =IFERROR('Cash Flow Data'!E6,0) -> -2656 | D71: =IFERROR('Cash Flow Data'!F6,0) -> -2853 | E71: =IFERROR('Cash Flow Data'!G6,0) -> -3692 | F71: =IFERROR('Cash Flow Data'!H6,0) -> -5743 | G71: =IFERROR('Cash Flow Data'!I6,0) -> -6621 | H71: =IFERROR('Cash Flow Data'!J6,0) -> -3560 | I71: =IFERROR('Cash Flow Data'!K6,0) -> 2069 | J71: =IFERROR('Cash Flow Data'!L6,0) -> 2326 | ... L71: =IFERROR('Cash Flow Data'!N6,0) -> 597
B72: Payables | C72: =IFERROR('Cash Flow Data'!E7,0) -> 8132 | D72: =IFERROR('Cash Flow Data'!F7,0) -> 4694 | E72: =IFERROR('Cash Flow Data'!G7,0) -> 3598 | F72: =IFERROR('Cash Flow Data'!H7,0) -> 3947 | G72: =IFERROR('Cash Flow Data'!I7,0) -> 9301 | H72: =IFERROR('Cash Flow Data'!J7,0) -> 7320 | I72: =IFERROR('Cash Flow Data'!K7,0) -> -4692 | J72: =IFERROR('Cash Flow Data'!L7,0) -> -8085 | ... L72: =IFERROR('Cash Flow Data'!N7,0) -> -7012
B73: Loans Advances | D73: =IFERROR('Cash Flow Data'!F8,0) -> 0 | E73: =IFERROR('Cash Flow Data'!G8,0) -> 0 | F73: =IFERROR('Cash Flow Data'!H8,0) -> -520 | G73: =IFERROR('Cash Flow Data'!I8,0) -> 0 | H73: =IFERROR('Cash Flow Data'!J8,0) -> 0 | I73: =IFERROR('Cash Flow Data'!K8,0) -> 0 | J73: =IFERROR('Cash Flow Data'!L8,0) -> 0 | K73: =IFERROR('Cash Flow Data'!M8,0) -> 0 | L73: =IFERROR('Cash Flow Data'!N8,0) -> 0
B74: Other WC items | C74: =IFERROR('Cash Flow Data'!E9,0) -> -303 | D74: =IFERROR('Cash Flow Data'!F9,0) -> 1870 | E74: =IFERROR('Cash Flow Data'!G9,0) -> -398 | F74: =IFERROR('Cash Flow Data'!H9,0) -> 5852 | G74: =IFERROR('Cash Flow Data'!I9,0) -> 4727 | H74: =IFERROR('Cash Flow Data'!J9,0) -> 494 | I74: =IFERROR('Cash Flow Data'!K9,0) -> 4512 | J74: =IFERROR('Cash Flow Data'!L9,0) -> 875 | ... L74: =IFERROR('Cash Flow Data'!N9,0) -> -4396
B75: Working capital changes | C75: =IFERROR('Cash Flow Data'!E10,0) -> -3 | D75: =IFERROR('Cash Flow Data'!F10,0) -> 4157 | E75: =IFERROR('Cash Flow Data'!G10,0) -> -3672 | F75: =IFERROR('Cash Flow Data'!H10,0) -> 1313 | G75: =IFERROR('Cash Flow Data'!I10,0) -> 3254 | H75: =IFERROR('Cash Flow Data'!J10,0) -> -6434 | I75: =IFERROR('Cash Flow Data'!K10,0) -> -7221 | J75: =IFERROR('Cash Flow Data'!L10,0) -> 5065 | ... L75: =IFERROR('Cash Flow Data'!N10,0) -> -10474
B76: Direct taxes | C76: =IFERROR('Cash Flow Data'!E11,0) -> -2240 | D76: =IFERROR('Cash Flow Data'!F11,0) -> -4308 | E76: =IFERROR('Cash Flow Data'!G11,0) -> -4194 | F76: =IFERROR('Cash Flow Data'!H11,0) -> -2040 | G76: =IFERROR('Cash Flow Data'!I11,0) -> -1895 | H76: =IFERROR('Cash Flow Data'!J11,0) -> -3021 | I76: =IFERROR('Cash Flow Data'!K11,0) -> -2659 | J76: =IFERROR('Cash Flow Data'!L11,0) -> -1785 | ... L76: =IFERROR('Cash Flow Data'!N11,0) -> -1910
B77: Cash From Operating Activities | C77: =SUM(C69:C76) -> 22159 | D77: =SUM(D69:D76) -> 40308 | E77: =SUM(E69:E76) -> 31860 | F77: =SUM(F69:F76) -> 39212 | G77: =SUM(G69:G76) -> 33454 | H77: =SUM(H69:H76) -> 17423 | I77: =SUM(I69:I76) -> 11671 | J77: =SUM(J69:J76) -> 31698 | ... L77: =SUM(L69:L76) -> 3808
B79: Investing Activities
B80: Fixed assets purchased | C80: =IFERROR('Cash Flow Data'!E13,0) -> -18863 | D80: =IFERROR('Cash Flow Data'!F13,0) -> -26975 | E80: =IFERROR('Cash Flow Data'!G13,0) -> -31962 | F80: =IFERROR('Cash Flow Data'!H13,0) -> -31503 | G80: =IFERROR('Cash Flow Data'!I13,0) -> -16072 | H80: =IFERROR('Cash Flow Data'!J13,0) -> -35079 | I80: =IFERROR('Cash Flow Data'!K13,0) -> -35304 | J80: =IFERROR('Cash Flow Data'!L13,0) -> -29702 | ... L80: =IFERROR('Cash Flow Data'!N13,0) -> -15168
B81: Fixed assets sold | C81: =IFERROR('Cash Flow Data'!E14,0) -> 37 | D81: =IFERROR('Cash Flow Data'!F14,0) -> 50 | E81: =IFERROR('Cash Flow Data'!G14,0) -> 74 | F81: =IFERROR('Cash Flow Data'!H14,0) -> 59 | G81: =IFERROR('Cash Flow Data'!I14,0) -> 53 | H81: =IFERROR('Cash Flow Data'!J14,0) -> 30 | I81: =IFERROR('Cash Flow Data'!K14,0) -> 67 | J81: =IFERROR('Cash Flow Data'!L14,0) -> 171 | ... L81: =IFERROR('Cash Flow Data'!N14,0) -> 230
B82: Investments purchased | C82: =IFERROR('Cash Flow Data'!E15,0) -> 73 | D82: =IFERROR('Cash Flow Data'!F15,0) -> -429 | E82: =IFERROR('Cash Flow Data'!G15,0) -> -5461 | F82: =IFERROR('Cash Flow Data'!H15,0) -> -4728 | G82: =IFERROR('Cash Flow Data'!I15,0) -> -6 | H82: =IFERROR('Cash Flow Data'!J15,0) -> -329 | I82: =IFERROR('Cash Flow Data'!K15,0) -> -130 | J82: =IFERROR('Cash Flow Data'!L15,0) -> -1439 | ... L82: =IFERROR('Cash Flow Data'!N15,0) -> -3008
B83: Investments sold | C83: =IFERROR('Cash Flow Data'!E16,0) -> 34 | D83: =IFERROR('Cash Flow Data'!F16,0) -> 4 | E83: =IFERROR('Cash Flow Data'!G16,0) -> 42 | F83: =IFERROR('Cash Flow Data'!H16,0) -> 89 | G83: =IFERROR('Cash Flow Data'!I16,0) -> 1965 | H83: =IFERROR('Cash Flow Data'!J16,0) -> 2381 | I83: =IFERROR('Cash Flow Data'!K16,0) -> 5644 | J83: =IFERROR('Cash Flow Data'!L16,0) -> 21 | ... L83: =IFERROR('Cash Flow Data'!N16,0) -> 104
B84: Interest received | C84: =IFERROR('Cash Flow Data'!E17,0) -> 713 | D84: =IFERROR('Cash Flow Data'!F17,0) -> 653 | E84: =IFERROR('Cash Flow Data'!G17,0) -> 698 | F84: =IFERROR('Cash Flow Data'!H17,0) -> 731 | G84: =IFERROR('Cash Flow Data'!I17,0) -> 638 | H84: =IFERROR('Cash Flow Data'!J17,0) -> 690 | I84: =IFERROR('Cash Flow Data'!K17,0) -> 761 | J84: =IFERROR('Cash Flow Data'!L17,0) -> 1104 | ... L84: =IFERROR('Cash Flow Data'!N17,0) -> 653
B85: Dividends received | C85: =IFERROR('Cash Flow Data'!E18,0) -> 95 | D85: =IFERROR('Cash Flow Data'!F18,0) -> 40 | E85: =IFERROR('Cash Flow Data'!G18,0) -> 80 | F85: =IFERROR('Cash Flow Data'!H18,0) -> 58 | G85: =IFERROR('Cash Flow Data'!I18,0) -> 620 | H85: =IFERROR('Cash Flow Data'!J18,0) -> 1797 | I85: =IFERROR('Cash Flow Data'!K18,0) -> 232 | J85: =IFERROR('Cash Flow Data'!L18,0) -> 21 | ... L85: =IFERROR('Cash Flow Data'!N18,0) -> 32
B86: Invest in subsidiaries | C86: =IFERROR('Cash Flow Data'!E19,0) -> 0 | D86: =IFERROR('Cash Flow Data'!F19,0) -> 0 | E86: =IFERROR('Cash Flow Data'!G19,0) -> 0 | F86: =IFERROR('Cash Flow Data'!H19,0) -> 0 | G86: =IFERROR('Cash Flow Data'!I19,0) -> 0 | H86: =IFERROR('Cash Flow Data'!J19,0) -> 0 | I86: =IFERROR('Cash Flow Data'!K19,0) -> 0 | J86: =IFERROR('Cash Flow Data'!L19,0) -> 0 | ... L86: =IFERROR('Cash Flow Data'!N19,0) -> 0
B87: Investment in group cos | C87: =IFERROR('Cash Flow Data'!E20,0) -> 0 | D87: =IFERROR('Cash Flow Data'!F20,0) -> 0 | E87: =IFERROR('Cash Flow Data'!G20,0) -> -160 | F87: =IFERROR('Cash Flow Data'!H20,0) -> 0 | G87: =IFERROR('Cash Flow Data'!I20,0) -> -107 | H87: =IFERROR('Cash Flow Data'!J20,0) -> -4 | I87: =IFERROR('Cash Flow Data'!K20,0) -> -9 | J87: =IFERROR('Cash Flow Data'!L20,0) -> -606 | ... L87: =IFERROR('Cash Flow Data'!N20,0) -> 0
B88: Redemp n Canc of Shares | C88: =IFERROR('Cash Flow Data'!E21,0) -> 0 | D88: =IFERROR('Cash Flow Data'!F21,0) -> 0 | E88: =IFERROR('Cash Flow Data'!G21,0) -> 0 | F88: =IFERROR('Cash Flow Data'!H21,0) -> 0 | G88: =IFERROR('Cash Flow Data'!I21,0) -> 0 | H88: =IFERROR('Cash Flow Data'!J21,0) -> 14 | I88: =IFERROR('Cash Flow Data'!K21,0) -> 533 | J88: =IFERROR('Cash Flow Data'!L21,0) -> 0 | ... L88: =IFERROR('Cash Flow Data'!N21,0) -> 0
B89: Acquisition of companies | C89: =IFERROR('Cash Flow Data'!E22,0) -> 0 | D89: =IFERROR('Cash Flow Data'!F22,0) -> -185 | E89: =IFERROR('Cash Flow Data'!G22,0) -> 0 | F89: =IFERROR('Cash Flow Data'!H22,0) -> -111 | G89: =IFERROR('Cash Flow Data'!I22,0) -> 0 | H89: =IFERROR('Cash Flow Data'!J22,0) -> 0 | I89: =IFERROR('Cash Flow Data'!K22,0) -> -8 | J89: =IFERROR('Cash Flow Data'!L22,0) -> -27 | ... L89: =IFERROR('Cash Flow Data'!N22,0) -> -98
B90: Inter corporate deposits | C90: =IFERROR('Cash Flow Data'!E23,0) -> 45 | D90: =IFERROR('Cash Flow Data'!F23,0) -> 0 | E90: =IFERROR('Cash Flow Data'!G23,0) -> 0 | F90: =IFERROR('Cash Flow Data'!H23,0) -> 0 | G90: =IFERROR('Cash Flow Data'!I23,0) -> 0 | H90: =IFERROR('Cash Flow Data'!J23,0) -> 0 | I90: =IFERROR('Cash Flow Data'!K23,0) -> 0 | J90: =IFERROR('Cash Flow Data'!L23,0) -> 0 | ... L90: =IFERROR('Cash Flow Data'!N23,0) -> 0
B91: Other investing items | C91: =IFERROR('Cash Flow Data'!E24,0) -> -5103 | D91: =IFERROR('Cash Flow Data'!F24,0) -> -1149 | E91: =IFERROR('Cash Flow Data'!G24,0) -> 456 | F91: =IFERROR('Cash Flow Data'!H24,0) -> -1289 | G91: =IFERROR('Cash Flow Data'!I24,0) -> -26663 | H91: =IFERROR('Cash Flow Data'!J24,0) -> 5360 | I91: =IFERROR('Cash Flow Data'!K24,0) -> 7335 | J91: =IFERROR('Cash Flow Data'!L24,0) -> -2659 | ... L91: =IFERROR('Cash Flow Data'!N24,0) -> 12813
B92: Cash from Investing Activities | C92: =SUM(C80:C91) -> -22969 | D92: =SUM(D80:D91) -> -27991 | E92: =SUM(E80:E91) -> -36233 | F92: =SUM(F80:F91) -> -36694 | G92: =SUM(G80:G91) -> -39572 | H92: =SUM(H80:H91) -> -25140 | I92: =SUM(I80:I91) -> -20879 | J92: =SUM(J80:J91) -> -33116 | ... L92: =SUM(L80:L91) -> -4442
B94: Financing Activities
B95: Proceeds from shares | C95: =IFERROR('Cash Flow Data'!E26,0) -> 1 | D95: =IFERROR('Cash Flow Data'!F26,0) -> 0 | E95: =IFERROR('Cash Flow Data'!G26,0) -> 0 | F95: =IFERROR('Cash Flow Data'!H26,0) -> 7433 | G95: =IFERROR('Cash Flow Data'!I26,0) -> 5 | H95: =IFERROR('Cash Flow Data'!J26,0) -> 0 | I95: =IFERROR('Cash Flow Data'!K26,0) -> 0 | J95: =IFERROR('Cash Flow Data'!L26,0) -> 3889 | ... L95: =IFERROR('Cash Flow Data'!N26,0) -> 19
B96: Redemption of debentures | C96: =IFERROR('Cash Flow Data'!E27,0) -> -97 | D96: =IFERROR('Cash Flow Data'!F27,0) -> -658 | E96: =IFERROR('Cash Flow Data'!G27,0) -> -744 | F96: =IFERROR('Cash Flow Data'!H27,0) -> 0 | G96: =IFERROR('Cash Flow Data'!I27,0) -> 0 | H96: =IFERROR('Cash Flow Data'!J27,0) -> 0 | I96: =IFERROR('Cash Flow Data'!K27,0) -> 0 | J96: =IFERROR('Cash Flow Data'!L27,0) -> 0 | ... L96: =IFERROR('Cash Flow Data'!N27,0) -> 0
B97: Proceeds from borrowings | C97: =IFERROR('Cash Flow Data'!E28,0) -> 27863 | D97: =IFERROR('Cash Flow Data'!F28,0) -> 33258 | E97: =IFERROR('Cash Flow Data'!G28,0) -> 36363 | F97: =IFERROR('Cash Flow Data'!H28,0) -> 19519 | G97: =IFERROR('Cash Flow Data'!I28,0) -> 33390 | H97: =IFERROR('Cash Flow Data'!J28,0) -> 37482 | I97: =IFERROR('Cash Flow Data'!K28,0) -> 51128 | J97: =IFERROR('Cash Flow Data'!L28,0) -> 38297 | ... L97: =IFERROR('Cash Flow Data'!N28,0) -> 46578
B98: Repayment of borrowings | C98: =IFERROR('Cash Flow Data'!E29,0) -> -20395 | D98: =IFERROR('Cash Flow Data'!F29,0) -> -29141 | E98: =IFERROR('Cash Flow Data'!G29,0) -> -23332 | F98: =IFERROR('Cash Flow Data'!H29,0) -> -24924 | G98: =IFERROR('Cash Flow Data'!I29,0) -> -21732 | H98: =IFERROR('Cash Flow Data'!J29,0) -> -29964 | I98: =IFERROR('Cash Flow Data'!K29,0) -> -35198 | J98: =IFERROR('Cash Flow Data'!L29,0) -> -29847 | ... L98: =IFERROR('Cash Flow Data'!N29,0) -> -42816
B99: Proceeds from deposits | C99: =IFERROR('Cash Flow Data'!E30,0) -> 0 | D99: =IFERROR('Cash Flow Data'!F30,0) -> 0 | E99: =IFERROR('Cash Flow Data'!G30,0) -> 0 | F99: =IFERROR('Cash Flow Data'!H30,0) -> 0 | G99: =IFERROR('Cash Flow Data'!I30,0) -> 0 | H99: =IFERROR('Cash Flow Data'!J30,0) -> 0 | I99: =IFERROR('Cash Flow Data'!K30,0) -> 0 | J99: =IFERROR('Cash Flow Data'!L30,0) -> 0 | ... L99: =IFERROR('Cash Flow Data'!N30,0) -> 0
B100: Interest paid fin | C100: =IFERROR('Cash Flow Data'!E31,0) -> -4666 | D100: =IFERROR('Cash Flow Data'!F31,0) -> -6171 | E100: =IFERROR('Cash Flow Data'!G31,0) -> -6307 | F100: =IFERROR('Cash Flow Data'!H31,0) -> -5716 | G100: =IFERROR('Cash Flow Data'!I31,0) -> -5336 | H100: =IFERROR('Cash Flow Data'!J31,0) -> -5411 | I100: =IFERROR('Cash Flow Data'!K31,0) -> -7005 | J100: =IFERROR('Cash Flow Data'!L31,0) -> -7518 | ... L100: =IFERROR('Cash Flow Data'!N31,0) -> -9251
B101: Dividends paid | C101: =IFERROR('Cash Flow Data'!E32,0) -> -1551 | D101: =IFERROR('Cash Flow Data'!F32,0) -> -722 | E101: =IFERROR('Cash Flow Data'!G32,0) -> -720 | F101: =IFERROR('Cash Flow Data'!H32,0) -> -108 | G101: =IFERROR('Cash Flow Data'!I32,0) -> -121 | H101: =IFERROR('Cash Flow Data'!J32,0) -> -96 | I101: =IFERROR('Cash Flow Data'!K32,0) -> -95 | J101: =IFERROR('Cash Flow Data'!L32,0) -> -57 | ... L101: =IFERROR('Cash Flow Data'!N32,0) -> -100
B102: Financial liabilities | C102: =IFERROR('Cash Flow Data'!E33,0) -> 0 | D102: =IFERROR('Cash Flow Data'!F33,0) -> 0 | E102: =IFERROR('Cash Flow Data'!G33,0) -> 0 | F102: =IFERROR('Cash Flow Data'!H33,0) -> 0 | G102: =IFERROR('Cash Flow Data'!I33,0) -> 0 | H102: =IFERROR('Cash Flow Data'!J33,0) -> 0 | I102: =IFERROR('Cash Flow Data'!K33,0) -> 0 | J102: =IFERROR('Cash Flow Data'!L33,0) -> -1346 | ... L102: =IFERROR('Cash Flow Data'!N33,0) -> -1559
B103: Other financing items | C103: =IFERROR('Cash Flow Data'!E34,0) -> -2849 | D103: =IFERROR('Cash Flow Data'!F34,0) -> -450 | E103: =IFERROR('Cash Flow Data'!G34,0) -> -57 | F103: =IFERROR('Cash Flow Data'!H34,0) -> 0 | G103: =IFERROR('Cash Flow Data'!I34,0) -> 0 | H103: =IFERROR('Cash Flow Data'!J34,0) -> 0 | I103: =IFERROR('Cash Flow Data'!K34,0) -> 0 | J103: =IFERROR('Cash Flow Data'!L34,0) -> -29 | ... L103: =IFERROR('Cash Flow Data'!N34,0) -> 3750
B104: Cash from Financing Activities | C104: =SUM(C95:C103) -> -1694 | D104: =SUM(D95:D103) -> -3884 | E104: =SUM(E95:E103) -> 5203 | F104: =SUM(F95:F103) -> -3796 | G104: =SUM(G95:G103) -> 6206 | H104: =SUM(H95:H103) -> 2011 | I104: =SUM(I95:I103) -> 8830 | J104: =SUM(J95:J103) -> 3389 | ... L104: =SUM(L95:L103) -> -3379
B106: Net Cash Flow | C106: =IFERROR(C77+C92+C104,0) -> -2504 | D106: =IFERROR(D77+D92+D104,0) -> 8433 | E106: =IFERROR(E77+E92+E104,0) -> 830 | F106: =IFERROR(F77+F92+F104,0) -> -1278 | G106: =IFERROR(G77+G92+G104,0) -> 88 | H106: =IFERROR(H77+H92+H104,0) -> -5706 | I106: =IFERROR(I77+I92+I104,0) -> -378 | J106: =IFERROR(J77+J92+J104,0) -> 1971 | ... L106: =IFERROR(L77+L92+L104,0) -> -4013

Sheet Ratio Analysis
B3: ="Ratio Analysis"&" - "&'Data Sheet'!B1 -> Ratio Analysis - TATA MOTORS LTD
B4: Years | C4: ='Data Sheet'!B16 -> 41364 | D4: ='Data Sheet'!C16 -> 41729 | E4: ='Data Sheet'!D16 -> 42094 | F4: ='Data Sheet'!E16 -> 42460 | G4: ='Data Sheet'!F16 -> 42825 | H4: ='Data Sheet'!G16 -> 43190 | I4: ='Data Sheet'!H16 -> 43555 | J4: ='Data Sheet'!I16 -> 43921 | ... L4: ='Data Sheet'!K16 -> 44651
B6: Sales Growth | D6: =IFERROR('Historical Data'!D6,0) -> 0.23327688 | E6: =IFERROR('Historical Data'!E6,0) -> 0.13024457 | F6: =IFERROR('Historical Data'!F6,0) -> 0.037569001 | G6: =IFERROR('Historical Data'!G6,0) -> -0.01228033 | H6: =IFERROR('Historical Data'!H6,0) -> 0.081047746 | I6: =IFERROR('Historical Data'!I6,0) -> 0.035629919 | J6: =IFERROR('Historical Data'!J6,0) -> -0.13536016 | K6: =IFERROR('Historical Data'!K6,0) -> -0.043181168 | L6: =IFERROR('Historical Data'!L6,0) -> 0.11472967
B7: EBITDA Growth | D7: =IFERROR('Historical Data'!D16/'Historical Data'!C16-1,0) -> 0.41703482 | E7: =IFERROR('Historical Data'!E16/'Historical Data'!D16-1,0) -> 0.12582115 | F7: =IFERROR('Historical Data'!F16/'Historical Data'!E16-1,0) -> -0.021494114 | G7: =IFERROR('Historical Data'!G16/'Historical Data'!F16-1,0) -> -0.22936587 | H7: =IFERROR('Historical Data'!H16/'Historical Data'!G16-1,0) -> 0.063165689 | I7: =IFERROR('Historical Data'!I16/'Historical Data'!H16-1,0) -> -0.21595203 | J7: =IFERROR('Historical Data'!J16/'Historical Data'!I16-1,0) -> -0.27072538 | K7: =IFERROR('Historical Data'!K16/'Historical Data'!J16-1,0) -> 0.79503554 | L7: =IFERROR('Historical Data'!L16/'Historical Data'!K16-1,0) -> -0.23437418
B8: EBT Growth | D8: =IFERROR('Historical Data'!D25/'Historical Data'!C25-1,0) -> 0.41619195 | E8: =IFERROR('Historical Data'!E25/'Historical Data'!D25-1,0) -> 0.10316382 | F8: =IFERROR('Historical Data'!F25/'Historical Data'!E25-1,0) -> -0.19978245 | G8: =IFERROR('Historical Data'!G25/'Historical Data'!F25-1,0) -> -0.55668252 | H8: =IFERROR('Historical Data'!H25/'Historical Data'!G25-1,0) -> -0.29861437 | I8: =IFERROR('Historical Data'!I25/'Historical Data'!H25-1,0) -> -1.8970951 | J8: =IFERROR('Historical Data'!J25/'Historical Data'!I25-1,0) -> 1.2800252 | K8: =IFERROR('Historical Data'!K25/'Historical Data'!J25-1,0) -> -1.060248 | L8: =IFERROR('Historical Data'!L25/'Historical Data'!K25-1,0) -> -15.649149
B9: Net Profit Growth | D9: =IFERROR('Historical Data'!D31/'Historical Data'!C31-1,0) -> 0.47662871 | E9: =IFERROR('Historical Data'!E31/'Historical Data'!D31-1,0) -> -0.064185676 | F9: =IFERROR('Historical Data'!F31/'Historical Data'!E31-1,0) -> 0.031824674 | G9: =IFERROR('Historical Data'!G31/'Historical Data'!F31-1,0) -> -0.69539895 | H9: =IFERROR('Historical Data'!H31/'Historical Data'!G31-1,0) -> -0.79011124 | I9: =IFERROR('Historical Data'!I31/'Historical Data'!H31-1,0) -> -3.5528471 | J9: =IFERROR('Historical Data'!J31/'Historical Data'!I31-1,0) -> 3.9286703 | K9: =IFERROR('Historical Data'!K31/'Historical Data'!J31-1,0) -> -0.82862505 | L9: =IFERROR('Historical Data'!L31/'Historical Data'!K31-1,0) -> 6.1952157
B10: Dividened Growth | D10: =IFERROR('Historical Data'!D39/'Historical Data'!C39-1,0) -> -0.0016039735 | E10: =IFERROR('Historical Data'!E39/'Historical Data'!D39-1,0) -> -1 | F10: =IFERROR('Historical Data'!F39/'Historical Data'!E39-1,0) -> 0 | G10: =IFERROR('Historical Data'!G39/'Historical Data'!F39-1,0) -> -1 | H10: =IFERROR('Historical Data'!H39/'Historical Data'!G39-1,0) -> 0 | I10: =IFERROR('Historical Data'!I39/'Historical Data'!H39-1,0) -> 0 | J10: =IFERROR('Historical Data'!J39/'Historical Data'!I39-1,0) -> 0 | K10: =IFERROR('Historical Data'!K39/'Historical Data'!J39-1,0) -> 0 | L10: =IFERROR('Historical Data'!L39/'Historical Data'!K39-1,0) -> 0
B12: Gross Margin | C12: =IFERROR('Historical Data'!C11/'Historical Data'!C5,0) -> 0.24658767 | D12: =IFERROR('Historical Data'!D11/'Historical Data'!D5,0) -> 0.22635301 | E12: =IFERROR('Historical Data'!E11/'Historical Data'!E5,0) -> 0.22914703 | F12: =IFERROR('Historical Data'!F11/'Historical Data'!F5,0) -> 0.24734524 | G12: =IFERROR('Historical Data'!G11/'Historical Data'!G5,0) -> 0.23819078 | H12: =IFERROR('Historical Data'!H11/'Historical Data'!H5,0) -> 0.2164999 | I12: =IFERROR('Historical Data'!I11/'Historical Data'!I5,0) -> 0.19571167 | J12: =IFERROR('Historical Data'!J11/'Historical Data'!J5,0) -> 0.19417127 | ... L12: =IFERROR('Historical Data'!L11/'Historical Data'!L5,0) -> 0.19807108
B13: EBITDA Margin | C13: =IFERROR('Historical Data'!C17,0) -> 0.13028036 | D13: =IFERROR('Historical Data'!D17,0) -> 0.1496921 | E13: =IFERROR('Historical Data'!E17,0) -> 0.14910626 | F13: =IFERROR('Historical Data'!F17,0) -> 0.14061845 | G13: =IFERROR('Historical Data'!G17,0) -> 0.10971269 | H13: =IFERROR('Historical Data'!H17,0) -> 0.10789788 | I13: =IFERROR('Historical Data'!I17,0) -> 0.081686629 | J13: =IFERROR('Historical Data'!J17,0) -> 0.068898034 | ... L13: =IFERROR('Historical Data'!L17,0) -> 0.088776328
B14: EBIT Margin | C14: =IFERROR(('Historical Data'!C16-'Historical Data'!C22)/'Historical Data'!C5,0) -> 0.090017786 | D14: =IFERROR(('Historical Data'!D16-'Historical Data'!D22)/'Historical Data'!D5,0) -> 0.10211238 | E14: =IFERROR(('Historical Data'!E16-'Historical Data'!E22)/'Historical Data'!E5,0) -> 0.098229671 | F14: =IFERROR(('Historical Data'!F16-'Historical Data'!F22)/'Historical Data'!F5,0) -> 0.079417028 | G14: =IFERROR(('Historical Data'!G16-'Historical Data'!G22)/'Historical Data'!G5,0) -> 0.043322301 | H14: =IFERROR(('Historical Data'!H16-'Historical Data'!H22)/'Historical Data'!H5,0) -> 0.033970412 | I14: =IFERROR(('Historical Data'!I16-'Historical Data'!I22)/'Historical Data'!I5,0) -> 0.0035560233 | J14: =IFERROR(('Historical Data'!J16-'Historical Data'!J22)/'Historical Data'!J5,0) -> -0.013170363 | ... L14: =IFERROR(('Historical Data'!L16-'Historical Data'!L22)/'Historical Data'!L5,0) -> -0.00041514993
B15: EBT Margin | C15: =IFERROR('Historical Data'!C26,0) -> 0.0711598 | D15: =IFERROR('Historical Data'!D26,0) -> 0.081713958 | E15: =IFERROR('Historical Data'!E26,0) -> 0.079756085 | F15: =IFERROR('Historical Data'!F26,0) -> 0.061511301 | G15: =IFERROR('Historical Data'!G26,0) -> 0.027608071 | H15: =IFERROR('Historical Data'!H26,0) -> 0.017912164 | I15: =IFERROR('Historical Data'!I26,0) -> -0.015516079 | J15: =IFERROR('Historical Data'!J26,0) -> -0.04091536 | ... L15: =IFERROR('Historical Data'!L26,0) -> -0.033856482
B16: Net Profit Margin | C16: =IFERROR('Historical Data'!C32,0) -> 0.051155529 | D16: =IFERROR('Historical Data'!D32,0) -> 0.061249606 | E16: =IFERROR('Historical Data'!E32,0) -> 0.050713147 | F16: =IFERROR('Historical Data'!F32,0) -> 0.050432382 | G16: =IFERROR('Historical Data'!G32,0) -> 0.015552749 | H16: =IFERROR('Historical Data'!H32,0) -> 0.0030196143 | I16: =IFERROR('Historical Data'!I32,0) -> -0.0074434057 | J16: =IFERROR('Historical Data'!J32,0) -> -0.042429334 | ... L16: =IFERROR('Historical Data'!L32,0) -> -0.049052155
B18: SalesExpenses % Sales | C18: =IFERROR('Historical Data'!C14,0) -> 0.11630731 | D18: =IFERROR('Historical Data'!D14,0) -> 0.076660909 | E18: =IFERROR('Historical Data'!E14,0) -> 0.08004078 | F18: =IFERROR('Historical Data'!F14,0) -> 0.10672679 | G18: =IFERROR('Historical Data'!G14,0) -> 0.1284781 | H18: =IFERROR('Historical Data'!H14,0) -> 0.10860202 | I18: =IFERROR('Historical Data'!I14,0) -> 0.11402505 | J18: =IFERROR('Historical Data'!J14,0) -> 0.12527324 | ... L18: =IFERROR('Historical Data'!L14,0) -> 0.10929475
B19: Depreciation % Sales | C19: =IFERROR('Historical Data'!C23,0) -> 0.040262576 | D19: =IFERROR('Historical Data'!D23,0) -> 0.047579718 | E19: =IFERROR('Historical Data'!E23,0) -> 0.050876584 | F19: =IFERROR('Historical Data'!F23,0) -> 0.061201426 | G19: =IFERROR('Historical Data'!G23,0) -> 0.066390387 | H19: =IFERROR('Historical Data'!H23,0) -> 0.073927472 | I19: =IFERROR('Historical Data'!I23,0) -> 0.078130605 | J19: =IFERROR('Historical Data'!J23,0) -> 0.082068398 | ... L19: =IFERROR('Historical Data'!L23,0) -> 0.089191478
B20: OperatingIncome % Sales | C20: =C14 -> 0.090017786 | D20: =D14 -> 0.10211238 | E20: =E14 -> 0.098229671 | F20: =F14 -> 0.079417028 | G20: =G14 -> 0.043322301 | H20: =H14 -> 0.033970412 | I20: =I14 -> 0.0035560233 | J20: =J14 -> -0.013170363 | ... L20: =L14 -> -0.00041514993
B22: Return on Capital Employed | C22: =IFERROR(('Historical Data'!C16-'Historical Data'!C22)/SUM('Historical Data'!C46:C48),0) -> 0.18603328 | D22: =IFERROR(('Historical Data'!D16-'Historical Data'!D22)/SUM('Historical Data'!D46:D48),0) -> 0.18832479 | E22: =IFERROR(('Historical Data'!E16-'Historical Data'!E22)/SUM('Historical Data'!E46:E48),0) -> 0.19904181 | F22: =IFERROR(('Historical Data'!F16-'Historical Data'!F22)/SUM('Historical Data'!F46:F48),0) -> 0.1462081 | G22: =IFERROR(('Historical Data'!G16-'Historical Data'!G22)/SUM('Historical Data'!G46:G48),0) -> 0.085490986 | H22: =IFERROR(('Historical Data'!H16-'Historical Data'!H22)/SUM('Historical Data'!H46:H48),0) -> 0.053716114 | I22: =IFERROR(('Historical Data'!I16-'Historical Data'!I22)/SUM('Historical Data'!I46:I48),0) -> 0.0064542734 | J22: =IFERROR(('Historical Data'!J16-'Historical Data'!J22)/SUM('Historical Data'!J46:J48),0) -> -0.018387083 | ... L22: =IFERROR(('Historical Data'!L16-'Historical Data'!L22)/SUM('Historical Data'!L46:L48),0) -> -0.00060520306
B23: Retained Earnings % | C23: =IFERROR('Historical Data'!C42,0) -> 0.93393209 | D23: =IFERROR('Historical Data'!D42,0) -> 0.95485721 | E23: =IFERROR('Historical Data'!E42,0) -> 1 | F23: =IFERROR('Historical Data'!F42,0) -> 0.99506766 | G23: =IFERROR('Historical Data'!G42,0) -> 1 | H23: =IFERROR('Historical Data'!H42,0) -> 1 | I23: =IFERROR('Historical Data'!I42,0) -> 0 | J23: =IFERROR('Historical Data'!J42,0) -> 0 | ... L23: =IFERROR('Historical Data'!L42,0) -> 0
B24: Return on Equity % | C24: =IFERROR('Historical Data'!C31/SUM('Historical Data'!C46:C47),0) -> 0.25660156 | D24: =IFERROR('Historical Data'!D31/SUM('Historical Data'!D46:D47),0) -> 0.2173814 | E24: =IFERROR('Historical Data'!E31/SUM('Historical Data'!E46:E47),0) -> 0.2372052 | F24: =IFERROR('Historical Data'!F31/SUM('Historical Data'!F46:F47),0) -> 0.17441317 | G24: =IFERROR('Historical Data'!G31/SUM('Historical Data'!G46:G47),0) -> 0.07224119 | H24: =IFERROR('Historical Data'!H31/SUM('Historical Data'!H46:H47),0) -> 0.0092254981 | I24: =IFERROR('Historical Data'!I31/SUM('Historical Data'!I46:I47),0) -> -0.037345737 | J24: =IFERROR('Historical Data'!J31/SUM('Historical Data'!J46:J47),0) -> -0.17805428 | ... L24: =IFERROR('Historical Data'!L31/SUM('Historical Data'!L46:L47),0) -> -0.30651638
B25: Self Sustained Growth rate | C25: =IFERROR(C23*C24,0) -> 0.23964843 | D25: =IFERROR(D23*D24,0) -> 0.2075682 | E25: =IFERROR(E23*E24,0) -> 0.2372052 | F25: =IFERROR(F23*F24,0) -> 0.1735529 | G25: =IFERROR(G23*G24,0) -> 0.07224119 | H25: =IFERROR(H23*H24,0) -> 0.0092254981 | I25: =IFERROR(I23*I24,0) -> 0 | J25: =IFERROR(J23*J24,0) -> 0 | ... L25: =IFERROR(L23*L24,0) -> 0
B26: Interest coverage ratio | C26: =IFERROR(('Historical Data'!C16-'Historical Data'!C22)/'Historical Data'!C19,0) -> 4.7734569 | D26: =IFERROR(('Historical Data'!D16-'Historical Data'!D22)/'Historical Data'!D19,0) -> 5.0058954 | E26: =IFERROR(('Historical Data'!E16-'Historical Data'!E22)/'Historical Data'!E19,0) -> 5.317304 | F26: =IFERROR(('Historical Data'!F16-'Historical Data'!F22)/'Historical Data'!F19,0) -> 4.4352864 | G26: =IFERROR(('Historical Data'!G16-'Historical Data'!G22)/'Historical Data'!G19,0) -> 2.7568835 | H26: =IFERROR(('Historical Data'!H16-'Historical Data'!H22)/'Historical Data'!H19,0) -> 2.1154494 | I26: =IFERROR(('Historical Data'!I16-'Historical Data'!I22)/'Historical Data'!I19,0) -> 0.18645157 | J26: =IFERROR(('Historical Data'!J16-'Historical Data'!J22)/'Historical Data'!J19,0) -> -0.47469327 | ... L26: =IFERROR(('Historical Data'!L16-'Historical Data'!L22)/'Historical Data'!L19,0) -> -0.012414276
B28: Debt Turnover ratio | C28: =IFERROR('Historical Data'!C5/'Historical Data'!C58,0) -> 17.226239 | D28: =IFERROR('Historical Data'!D5/'Historical Data'!D58,0) -> 22.018971 | E28: =IFERROR('Historical Data'!E5/'Historical Data'!E58,0) -> 20.920168 | F28: =IFERROR('Historical Data'!F5/'Historical Data'!F58,0) -> 20.119918 | G28: =IFERROR('Historical Data'!G5/'Historical Data'!G58,0) -> 19.160353 | H28: =IFERROR('Historical Data'!H5/'Historical Data'!H58,0) -> 14.655712 | I28: =IFERROR('Historical Data'!I5/'Historical Data'!I58,0) -> 15.894699 | J28: =IFERROR('Historical Data'!J5/'Historical Data'!J58,0) -> 23.366617 | ... L28: =IFERROR('Historical Data'!L5/'Historical Data'!L58,0) -> 22.379918
B29: Credit Turnover ratio | C29: =IFERROR('Historical Data'!C5/'Historical Data'!C49,0) -> 2.4525851 | D29: =IFERROR('Historical Data'!D5/'Historical Data'!D49,0) -> 2.5258516 | E29: =IFERROR('Historical Data'!E5/'Historical Data'!E49,0) -> 2.4493011 | F29: =IFERROR('Historical Data'!F5/'Historical Data'!F49,0) -> 2.3769604 | G29: =IFERROR('Historical Data'!G5/'Historical Data'!G49,0) -> 1.9842808 | H29: =IFERROR('Historical Data'!H5/'Historical Data'!H49,0) -> 2.041478 | I29: =IFERROR('Historical Data'!I5/'Historical Data'!I49,0) -> 2.1667848 | J29: =IFERROR('Historical Data'!J5/'Historical Data'!J49,0) -> 1.9602535 | ... L29: =IFERROR('Historical Data'!L5/'Historical Data'!L49,0) -> 2.0170312
B30: Inventory Turnover | C30: =IFERROR('Historical Data'!C5/'Historical Data'!C59,0) -> 8.974393 | D30: =IFERROR('Historical Data'!D5/'Historical Data'!D59,0) -> 8.5378094 | E30: =IFERROR('Historical Data'!E5/'Historical Data'!E59,0) -> 8.990022 | F30: =IFERROR('Historical Data'!F5/'Historical Data'!F59,0) -> 8.3613381 | G30: =IFERROR('Historical Data'!G5/'Historical Data'!G59,0) -> 7.6867643 | H30: =IFERROR('Historical Data'!H5/'Historical Data'!H59,0) -> 6.9190052 | I30: =IFERROR('Historical Data'!I5/'Historical Data'!I59,0) -> 7.7392856 | J30: =IFERROR('Historical Data'!J5/'Historical Data'!J59,0) -> 6.9698269 | ... L30: =IFERROR('Historical Data'!L5/'Historical Data'!L59,0) -> 7.9015588
B31: Fixed Assest Turnover | C31: =IFERROR('Historical Data'!C5/'Historical Data'!C52,0) -> 3.4009513 | D31: =IFERROR('Historical Data'!D5/'Historical Data'!D52,0) -> 3.3699238 | E31: =IFERROR('Historical Data'!E5/'Historical Data'!E52,0) -> 2.9742371 | F31: =IFERROR('Historical Data'!F5/'Historical Data'!F52,0) -> 2.5463128 | G31: =IFERROR('Historical Data'!G5/'Historical Data'!G52,0) -> 2.8109343 | H31: =IFERROR('Historical Data'!H5/'Historical Data'!H52,0) -> 2.4012949 | I31: =IFERROR('Historical Data'!I5/'Historical Data'!I52,0) -> 2.714432 | J31: =IFERROR('Historical Data'!J5/'Historical Data'!J52,0) -> 2.0539206 | ... L31: =IFERROR('Historical Data'!L5/'Historical Data'!L52,0) -> 2.0053489
B32: Capital Turnover Ratio | C32: =IFERROR('Historical Data'!C5/SUM('Historical Data'!C46:C47),0) -> 5.0161061 | D32: =IFERROR('Historical Data'!D5/SUM('Historical Data'!D46:D47),0) -> 3.5491069 | E32: =IFERROR('Historical Data'!E5/SUM('Historical Data'!E46:E47),0) -> 4.6773907 | F32: =IFERROR('Historical Data'!F5/SUM('Historical Data'!F46:F47),0) -> 3.4583567 | G32: =IFERROR('Historical Data'!G5/SUM('Historical Data'!G46:G47),0) -> 4.6449144 | H32: =IFERROR('Historical Data'!H5/SUM('Historical Data'!H46:H47),0) -> 3.0551909 | I32: =IFERROR('Historical Data'!I5/SUM('Historical Data'!I46:I47),0) -> 5.0172916 | J32: =IFERROR('Historical Data'!J5/SUM('Historical Data'!J46:J47),0) -> 4.1964901 | ... L32: =IFERROR('Historical Data'!L5/SUM('Historical Data'!L46:L47),0) -> 6.2487853
B35: Debtor days | C35: =IFERROR(365/C28,0) -> 21.188606 | D35: =IFERROR(365/D28,0) -> 16.576615 | E35: =IFERROR(365/E28,0) -> 17.447278 | F35: =IFERROR(365/F28,0) -> 18.141227 | G35: =IFERROR(365/G28,0) -> 19.049753 | H35: =IFERROR(365/H28,0) -> 24.904965 | I35: =IFERROR(365/I28,0) -> 22.963631 | J35: =IFERROR(365/J28,0) -> 15.620575 | ... L35: =IFERROR(365/L28,0) -> 16.309265
B36: Payable days | C36: =IFERROR(365/C29,0) -> 148.82256 | D36: =IFERROR(365/D29,0) -> 144.50572 | E36: =IFERROR(365/E29,0) -> 149.02211 | F36: =IFERROR(365/F29,0) -> 153.55746 | G36: =IFERROR(365/G29,0) -> 183.94574 | H36: =IFERROR(365/H29,0) -> 178.79203 | I36: =IFERROR(365/I29,0) -> 168.45236 | J36: =IFERROR(365/J29,0) -> 186.20041 | ... L36: =IFERROR(365/L29,0) -> 180.95902
B37: Inventory days | C37: =IFERROR(365/C30,0) -> 40.671274 | D37: =IFERROR(365/D30,0) -> 42.751013 | E37: =IFERROR(365/E30,0) -> 40.600568 | F37: =IFERROR(365/F30,0) -> 43.6533 | G37: =IFERROR(365/G30,0) -> 47.484219 | H37: =IFERROR(365/H30,0) -> 52.753249 | I37: =IFERROR(365/I30,0) -> 47.161976 | J37: =IFERROR(365/J30,0) -> 52.368589 | ... L37: =IFERROR(365/L30,0) -> 46.193417
B38: Cash Conversion Cycle | C38: =IFERROR(SUM(C35,C37)-C36,0) -> -86.962684 | D38: =IFERROR(SUM(D35,D37)-D36,0) -> -85.178089 | E38: =IFERROR(SUM(E35,E37)-E36,0) -> -90.974259 | F38: =IFERROR(SUM(F35,F37)-F36,0) -> -91.762933 | G38: =IFERROR(SUM(G35,G37)-G36,0) -> -117.41177 | H38: =IFERROR(SUM(H35,H37)-H36,0) -> -101.13382 | I38: =IFERROR(SUM(I35,I37)-I36,0) -> -98.326751 | J38: =IFERROR(SUM(J35,J37)-J36,0) -> -118.21124 | ... L38: =IFERROR(SUM(L35,L37)-L36,0) -> -118.45634
B40: CFO/sales | C40: =IFERROR('Historical Data'!C77/'Historical Data'!C5,0) -> 0.11737213 | D40: =IFERROR('Historical Data'!D77/'Historical Data'!D5,0) -> 0.1731193 | E40: =IFERROR('Historical Data'!E77/'Historical Data'!E5,0) -> 0.1210675 | F40: =IFERROR('Historical Data'!F77/'Historical Data'!F5,0) -> 0.14360971 | G40: =IFERROR('Historical Data'!G77/'Historical Data'!G5,0) -> 0.12404497 | H40: =IFERROR('Historical Data'!H77/'Historical Data'!H5,0) -> 0.059759806 | I40: =IFERROR('Historical Data'!I77/'Historical Data'!I5,0) -> 0.03865358 | J40: =IFERROR('Historical Data'!J77/'Historical Data'!J5,0) -> 0.12141666 | ... L40: =IFERROR('Historical Data'!L77/'Historical Data'!L5,0) -> 0.013675527
B41: CFO/Total Assests | C41: =IFERROR('Historical Data'!C77/'Historical Data'!C63,0) -> 0.13164021 | D41: =IFERROR('Historical Data'!D77/'Historical Data'!D63,0) -> 0.18453848 | E41: =IFERROR('Historical Data'!E77/'Historical Data'!E63,0) -> 0.13425206 | F41: =IFERROR('Historical Data'!F77/'Historical Data'!F63,0) -> 0.14899075 | G41: =IFERROR('Historical Data'!G77/'Historical Data'!G63,0) -> 0.12273078 | H41: =IFERROR('Historical Data'!H77/'Historical Data'!H63,0) -> 0.05325011 | I41: =IFERROR('Historical Data'!I77/'Historical Data'!I63,0) -> 0.038177516 | J41: =IFERROR('Historical Data'!J77/'Historical Data'!J63,0) -> 0.099000751 | ... L41: =IFERROR('Historical Data'!L77/'Historical Data'!L63,0) -> 0.011572305
B42: CFO/Total Debt | C42: =IFERROR('Historical Data'!C77/'Historical Data'!C48,0) -> 0.41252364 | D42: =IFERROR('Historical Data'!D77/'Historical Data'!D48,0) -> 0.66468477 | E42: =IFERROR('Historical Data'!E77/'Historical Data'!E48,0) -> 0.43281933 | F42: =IFERROR('Historical Data'!F77/'Historical Data'!F48,0) -> 0.56534058 | G42: =IFERROR('Historical Data'!G77/'Historical Data'!G48,0) -> 0.42560186 | H42: =IFERROR('Historical Data'!H77/'Historical Data'!H48,0) -> 0.19587305 | I42: =IFERROR('Historical Data'!I77/'Historical Data'!I48,0) -> 0.10992195 | J42: =IFERROR('Historical Data'!J77/'Historical Data'!J48,0) -> 0.25401554 | ... L42: =IFERROR('Historical Data'!L77/'Historical Data'!L48,0) -> 0.026002221

Sheet Data>

Sheet Data Sheet
A1: COMPANY NAME | B1: TATA MOTORS LTD | E1: =IF(B2<>B3, "A NEW VERSION OF THE WORKSHEET IS AVAILABLE", "")
A2: LATEST VERSION | B2: 2.1 | E2: PLEASE DO NOT MAKE ANY CHANGES TO THIS SHEET
A3: CURRENT VERSION | B3: 2.1
A5: META
A6: Number of shares | B6: =IF(B9>0, B9/B8, 0) -> 358.58909
A7: Face Value | B7: 2
A8: Current Price | B8: 411.5
A9: Market Capitalization | B9: 147559.41
A15: PROFIT & LOSS | B15: =B26+B34 -> 32432.08 | K15: =K17-K18-K20-K21-K22-K23-K19 -> 29129.19
A16: Report Date | B16: 41364 | C16: 41729 | D16: 42094 | E16: 42460 | F16: 42825 | G16: 43190 | H16: 43555 | I16: 43921 | J16: 44286 | K16: 44651
A17: Sales | B17: 188792.69 | C17: 232833.66 | D17: 263158.98 | E17: 273045.6 | F17: 269692.51 | G17: 291550.48 | H17: 301938.4 | I17: 261067.97 | J17: 249794.75 | K17: 278453.62
A18: Raw Material Cost | B18: 123117.34 | C18: 146426.99 | D18: 163250.36 | E18: 166134.01 | F18: 173294.08 | G18: 187896.58 | H18: 194267.91 | I18: 164899.82 | J18: 153607.36 | K18: 179295.33
A19: Change in Inventory | B19: 3029.29 | C19: 2840.58 | D19: 3330.35 | E19: 2750.99 | F19: 7399.92 | G19: 2046.58 | H19: -2053.28 | I19: -2231.19 | J19: -4684.16 | K19: -1590.49
A20: Power and Fuel | B20: 1077.77 | C20: 1128.69 | D20: 1121.75 | E20: 1143.63 | F20: 1159.82 | G20: 1308.08 | H20: 1585.93 | I20: 1264.95 | J20: 1112.87 | K20: 2178.29
A21: Other Mfr. Exp | B21: 4440.73 | C21: 13806.04 | D21: 16173.17 | E21: 12101.53 | F21: 10067.37 | G21: 10971.66 | H21: 11694.54 | I21: 11541.51 | J21: 8273.17 | K21: 9427.38
A22: Employee Cost | B22: 16632.19 | C22: 21609.92 | D22: 25641.95 | E22: 28880.89 | F22: 28332.89 | G22: 30300.09 | H22: 33243.87 | I22: 30438.6 | J22: 27648.48 | K22: 30808.52
A23: Selling and admin | B23: 16632.91 | C23: 22357.79 | D23: 23603.01 | E23: 21991.9 | F23: 30039.38 | G23: 31004.58 | H23: 32719.8 | I23: 29248.32 | J23: 23015.79 | K23: 29205.4
A24: Other Expenses | B24: 5325.06 | C24: -4508.55 | D24: -2539.56 | E24: 7149.38 | F24: 4610.2 | G24: 658.39 | H24: 1708.74 | I24: 3456.51 | J24: -834.51 | K24: 1228.12
A25: Other Income | B25: 212.88 | C25: -156.79 | D25: 714.03 | E25: -2669.62 | F25: 1869.1 | G25: 5932.73 | H25: -26686.25 | I25: 101.71 | J25: -11117.83 | K25: 2424.05
A26: Depreciation | B26: 7601.28 | C26: 11078.16 | D26: 13388.63 | E26: 16710.78 | F26: 17904.99 | G26: 21553.59 | H26: 23590.63 | I26: 21425.43 | J26: 23546.71 | K26: 24835.69
A27: Interest | B27: 3560.25 | C27: 4749.44 | D27: 4861.49 | E27: 4889.08 | F27: 4238.01 | G27: 4681.79 | H27: 5758.6 | I27: 7243.33 | J27: 8097.17 | K27: 9311.86
... A30: Net profit | B30: 9892.61 | C30: 13991.02 | D30: 13986.29 | E30: 11579.31 | F30: 7454.36 | G30: 8988.91 | H30: -28826.23 | I30: -12070.85 | J30: -13451.39 | K30: -11441.47
A31: Dividend Amount | B31: 638.07 | C31: 643.78 | E31: 67.92
A32: Effective Tax Rate | B32: =B29/B28 -> 0.27673252 | C32: =C29/C28 -> 0.25251988 | D32: =D29/D28 -> 0.35216629 | E32: =E29/E28 -> 0.21415116 | F32: =F29/F28 -> 0.34903954 | G32: =G29/G28 -> 0.38923517 | H32: =H29/H28 -> 0.077697184 | I32: =I29/I28 -> -0.037358294 | ... K32: =K29/K28 -> -0.60417568
A34: EBITDA | B34: =+B30+B29+B27+B26 -> 24830.8 | C34: =+C30+C29+C27+C26 -> 34583.41 | D34: =+D30+D29+D27+D26 -> 39879.32 | E34: =+E30+E29+E27+E26 -> 36204.22 | F34: =+F30+F29+F27+F26 -> 32848.59 | G34: =+G30+G29+G27+G26 -> 39566.22 | H34: =+H30+H29+H27+H26 -> -1914.45 | I34: =+I30+I29+I27+I26 -> 16993.16 | ... K34: =+K30+K29+K27+K26 -> 26937.37
A40: Quarters
A41: Report Date | B41: 44012 | C41: 44104 | D41: 44196 | E41: 44286 | F41: 44377 | G41: 44469 | H41: 44561 | I41: 44651 | J41: 44742 | K41: 44834
A42: Sales | B42: 31983.06 | C42: 53530 | D42: 75653.79 | E42: 88627.9 | F42: 66406.45 | G42: 61378.82 | H42: 72229.29 | I42: 78439.06 | J42: 71934.66 | K42: 79611.37
A43: Expenses | B43: 31300.36 | C43: 47431.7 | D43: 63521.09 | E43: 75254.17 | F43: 61163.78 | G43: 57262.21 | H43: 65151.27 | I43: 70156.27 | J43: 69521.93 | K43: 74039.06
A44: Other Income | B44: 609.75 | C44: 638.1 | D44: 289.37 | E44: -12655.05 | F44: 584.12 | G44: 862.46 | H44: 788.73 | I44: 188.74 | J44: 2380.98 | K44: 1351.14
A45: Depreciation | B45: 5599.37 | C45: 5601.47 | D45: 6128.75 | E45: 6217.12 | F45: 6202.13 | G45: 6123.32 | H45: 6078.13 | I45: 6432.11 | J45: 5841.04 | K45: 5897.34
A46: Interest | B46: 1876.81 | C46: 1949.6 | D46: 2125.93 | E46: 2144.83 | F46: 2203.3 | G46: 2327.3 | H46: 2400.74 | I46: 2380.52 | J46: 2420.72 | K46: 2487.26
A47: Profit before tax | B47: -6183.73 | C47: -814.67 | D47: 4167.39 | E47: -7643.27 | F47: -2578.64 | G47: -3471.55 | H47: -612.12 | I47: -341.1 | J47: -3468.05 | K47: -1461.15
A48: Tax | B48: 2200.49 | C48: -471.39 | D48: 945.18 | E48: -132.42 | F48: 1741.96 | G48: 1005.06 | H48: 726.05 | I48: 758.22 | J48: 1518.96 | K48: -457.08
A49: Net profit | B49: -8437.99 | C49: -314.45 | D49: 2906.45 | E49: -7605.4 | F49: -4450.92 | G49: -4441.57 | H49: -1516.14 | I49: -1032.84 | J49: -5006.6 | K49: -944.61
A50: Operating Profit | B50: 682.7 | C50: 6098.3 | D50: 12132.7 | E50: 13373.73 | F50: 5242.67 | G50: 4116.61 | H50: 7078.02 | I50: 8282.79 | J50: 2412.73 | K50: 5572.31
A51: EBITDA | B51: =B49+B48+B46+B45 -> 1238.68 | C51: =C49+C48+C46+C45 -> 6765.23 | D51: =D49+D48+D46+D45 -> 12106.31 | E51: =E49+E48+E46+E45 -> 624.13 | F51: =F49+F48+F46+F45 -> 5696.47 | G51: =G49+G48+G46+G45 -> 5014.11 | H51: =H49+H48+H46+H45 -> 7688.78 | I51: =I49+I48+I46+I45 -> 8538.01 | ... K51: =K49+K48+K46+K45 -> 6982.91
A55: BALANCE SHEET
A56: Report Date | B56: 41364 | C56: 41729 | D56: 42094 | E56: 42460 | F56: 42825 | G56: 43190 | H56: 43555 | I56: 43921 | J56: 44286 | K56: 44651
A57: Equity Share Capital | B57: 638.07 | C57: 643.78 | D57: 643.78 | E57: 679.18 | F57: 679.22 | G57: 679.22 | H57: 679.22 | I57: 719.54 | J57: 765.81 | K57: 765.88
A58: Reserves | B58: 36999.23 | C58: 64959.67 | D58: 55618.14 | E58: 78273.23 | F58: 57382.67 | G58: 94748.69 | H58: 59500.34 | I58: 61491.49 | J58: 54480.91 | K58: 43795.36
A59: Borrowings | B59: 53715.71 | C59: 60642.28 | D59: 73610.39 | E59: 69359.96 | F59: 78603.98 | G59: 88950.47 | H59: 106175.34 | I59: 124787.64 | J59: 142130.57 | K59: 146449.03
A60: Other Liabilities | B60: 76977.02 | C60: 92180.26 | D60: 107442.48 | E60: 114871.75 | F60: 135914.49 | G60: 142813.43 | H60: 139348.59 | I60: 133180.72 | J60: 144192.62 | K60: 138051.22
A61: Total | B61: 168330.03 | C61: 218425.99 | D61: 237314.79 | E61: 263184.12 | F61: 272580.36 | G61: 327191.81 | H61: 305703.49 | I61: 320179.39 | J61: 341569.91 | K61: 329061.49
A62: Net Block | B62: 55511.73 | C62: 69091.67 | D62: 88479.49 | E62: 107231.76 | F62: 95944.08 | G62: 121413.86 | H62: 111234.47 | I62: 127107.14 | J62: 138707.61 | K62: 138855.45
A63: Capital Work in Progress | B63: 18453.55 | C63: 33262.56 | D63: 28640.09 | E63: 25918.94 | F63: 33698.84 | G63: 40033.5 | H63: 31883.84 | I63: 35622.29 | J63: 20963.93 | K63: 10251.09
A64: Investments | B64: 8764.73 | C64: 10686.67 | D64: 15336.74 | E64: 23767.02 | F64: 20337.92 | G64: 20812.75 | H64: 15770.72 | I64: 16308.48 | J64: 24620.28 | K64: 29379.53
A65: Other Assets | B65: 85600.02 | C65: 105385.09 | D65: 104858.47 | E65: 106266.4 | F65: 122599.52 | G65: 144931.7 | H65: 146814.46 | I65: 141141.48 | J65: 157278.09 | K65: 150575.42
A66: Total | B66: 168330.03 | C66: 218425.99 | D66: 237314.79 | E66: 263184.12 | F66: 272580.36 | G66: 327191.81 | H66: 305703.49 | I66: 320179.39 | J66: 341569.91 | K66: 329061.49
A67: Receivables | B67: 10959.6 | C67: 10574.23 | D67: 12579.2 | E67: 13570.91 | F67: 14075.55 | G67: 19893.3 | H67: 18996.17 | I67: 11172.69 | J67: 12679.08 | K67: 12442.12
... A70: No. of Equity Shares | B70: 3190115771 | C70: 3218930000 | D70: 3218930067 | E70: 3395930306 | F70: 3396100719 | G70: 3396100719 | H70: 3396100719 | I70: 3597726185 | J70: 3829060661 | K70: 3829414903
A71: New Bonus Shares
A72: Face value | B72: 2 | C72: 2 | D72: 2 | E72: 2 | F72: 2 | G72: 2 | H72: 2 | I72: 2 | J72: 2 | K72: 2
H73: =H62-G62+H45 -> -4101.26 | I73: =I62-H62+I45 -> 22304.78 | J73: =J62-I62+J45 -> 17441.51 | K73: =K62-J62+K45 -> 6045.18
A80: CASH FLOW:
A81: Report Date | B81: 41364 | C81: 41729 | D81: 42094 | E81: 42460 | F81: 42825 | G81: 43190 | H81: 43555 | I81: 43921 | J81: 44286 | K81: 44651
A82: Cash from Operating Activity | B82: 22162.61 | C82: 36151.16 | D82: 35531.26 | E82: 37899.54 | F82: 30199.25 | G82: 23857.42 | H82: 18890.75 | I82: 26632.94 | J82: 29000.51 | K82: 14282.83
A83: Cash from Investing Activity | B83: -22969.45 | C83: -27990.91 | D83: -36232.35 | E83: -36693.9 | F83: -39571.4 | G83: -25139.14 | H83: -20878.07 | I83: -33114.55 | J83: -25672.5 | K83: -4443.66
A84: Cash from Financing Activity | B84: -1692.08 | C84: -3883.24 | D84: 5201.44 | E84: -3795.12 | F84: 6205.3 | G84: 2011.71 | H84: 8830.37 | I84: 3389.61 | J84: 9904.2 | K84: -3380.17
A85: Net Cash Flow | B85: -2498.92 | C85: 4277.01 | D85: 4500.35 | E85: -2589.48 | F85: -3166.85 | G85: 729.99 | H85: 6843.05 | I85: -3092 | J85: 13232.21 | K85: 6459
A90: PRICE: | B90: 266.3 | C90: 394.42 | D90: 544.37 | E90: 386.6 | F90: 465.85 | G90: 326.85 | H90: 174.25 | I90: 71.05 | J90: 301.8 | K90: 433.75
A92: DERIVED:
A93: Adjusted Equity Shares in Cr | B93: 285.72 | C93: 288.74 | D93: 288.74 | E93: 288.72 | F93: 288.73 | G93: 288.73 | H93: 288.73 | I93: 308.9 | J93: 332.03 | K93: 332.07

Sheet RawFS
B9: Particulars | C9: 42064 | D9: 42430 | E9: 42795 | F9: 43160 | G9: 43525 | H9: 43891 | I9: 44256 | J9: 44621 | K9: 44986 | L9: 45352 | M9: 45717 | N9: 46082
B11: Equity Capital | C11: 644 | D11: 679 | E11: 679 | F11: 679 | G11: 679 | H11: 720 | I11: 766 | J11: 766 | K11: 766 | L11: 767 | M11: 736 | N11: 737
B12: Reserves | C12: 55618 | D12: 78273 | E12: 57383 | F12: 94749 | G12: 59500 | H12: 62359 | I12: 54481 | J12: 43795 | K12: 44556 | L12: 84151 | M12: 115408 | N12: 111331
B13: Borrowings - | C13: 73610 | D13: 69360 | E13: 78604 | F13: 88950 | G13: 106175 | H13: 124788 | I13: 142131 | J13: 146449 | K13: 134113 | L13: 107264 | M13: 71540 | N13: 79109
B14: Long term Borrowings | C14: 56071 | D14: 50510 | E14: 60629 | F14: 61200 | G14: 70818 | H14: 83316 | I14: 93113 | J14: 97759 | K14: 88696 | L14: 62149 | M14: 40217 | N14: 44248
B15: Short term Borrowings | C15: 13140 | D15: 11451 | E15: 13860 | F15: 16795 | G15: 20150 | H15: 16363 | I15: 42792 | J15: 41918 | K15: 36965 | L15: 36352 | M15: 22282 | N15: 25705
B16: Lease Liabilities | C16: 0 | D16: 0 | E16: 0 | F16: 0 | G16: 173 | H16: 5977 | I16: 6226 | J16: 6772 | K16: 8453 | L16: 8763 | M16: 9041 | N16: 9156
B17: Other Borrowings | C17: 4399 | D17: 7399 | E17: 4115 | F17: 10956 | G17: 15034 | H17: 19132 | I17: 0 | J17: 0 | K17: 0 | L17: 0 | M17: 0 | N17: 0
B18: Other Liabilities - | C18: 107442 | D18: 114872 | E18: 135914 | F18: 142813 | G18: 139349 | H18: 132313 | I18: 144193 | J18: 138051 | K18: 155239 | L18: 177339 | M18: 189289 | N18: 188012
B19: Non controlling int | C19: 433 | D19: 433 | E19: 453 | F19: 525 | G19: 523 | H19: 814 | I19: 1573 | J19: 4271 | K19: 7278 | L19: 8176 | M19: 6610 | N19: 6774
B20: Trade Payables | C20: 57407 | D20: 61562 | E20: 62533 | F20: 76940 | G20: 71691 | H20: 66398 | I20: 76040 | J20: 69750 | K20: 79252 | L20: 93978 | M20: 97368 | N20: 92780
B21: Advance from Customers | C21: 2289 | D21: 2165 | E21: 1711 | F21: 0 | G21: 0 | H21: 0 | I21: 0 | J21: 0 | K21: 0 | L21: 0 | M21: 0 | N21: 0
... B44: Total Assets | C44: 237315 | D44: 263184 | E44: 272580 | F44: 327192 | G44: 305703 | H44: 320179 | I44: 341570 | J44: 329061 | K44: 334674 | L44: 369521 | M44: 376973 | N44: 379189
C47: 42064 | D47: 42430 | E47: 42795 | F47: 43160 | G47: 43525 | H47: 43891 | I47: 44256 | J47: 44621 | K47: 44986 | L47: 45352 | M47: 45717 | N47: 46082
B48: Cash from Operating Activity - | C48: 35531 | D48: 37900 | E48: 30199 | F48: 23857 | G48: 18891 | H48: 26633 | I48: 29001 | J48: 14283 | K48: 35388 | L48: 67915 | M48: 63102 | N48: 13041
B49: Profit from operations | C49: 43397 | D49: 38626 | E49: 28840 | F49: 33312 | G49: 28771 | H49: 23352 | I49: 31198 | J49: 26943 | K49: 41694 | L49: 65106 | M49: 58937 | N49: 25393
B50: Receivables | C50: -3179 | D50: -2223 | E50: -4152 | F50: -10688 | G50: -9109 | H50: 9950 | I50: -5505 | J50: 185 | K50: -2213 | L50: -1876 | M50: 3573 | N50: -1587
B51: Inventory | C51: -3692 | D51: -5743 | E51: -6621 | F51: -3560 | G51: 2069 | H51: 2326 | I51: 3814 | J51: 472 | K51: -5665 | L51: -7265 | M51: 2127 | N51: -4318
B52: Payables | C52: 3598 | D52: 3947 | E52: 9301 | F52: 7320 | G52: -4692 | H52: -8085 | I52: 5748 | J52: -7012 | K52: 6945 | L52: 13706 | M52: 1303 | N52: -1973
B53: Loans Advances | C53: 0 | D53: -520 | E53: 0 | F53: 0 | G53: 0 | H53: 0 | I53: 0 | J53: 0 | K53: 0 | L53: 0 | M53: 0 | N53: 0
B54: Other WC items | C54: -398 | D54: 5852 | E54: 4727 | F54: 494 | G54: 4512 | H54: 875 | I54: -4150 | J54: -4396 | K54: -2194 | L54: 2760 | M54: 1153 | N54: -1160
B55: Working capital changes | C55: -3672 | D55: 1313 | E55: 3254 | F55: -6434 | G55: -7221 | H55: 5065 | I55: -93 | J55: -10750 | K55: -3127 | L55: 7325 | M55: 8156 | N55: -9038
B56: Direct taxes | C56: -4194 | D56: -2040 | E56: -1895 | F56: -3021 | G56: -2659 | H56: -1785 | I56: -2105 | J56: -1910 | K56: -3179 | L56: -4516 | M56: -3991 | N56: -3314
B57: Cash from Investing Activity - | C57: -36232 | D57: -36694 | E57: -39571 | F57: -25139 | G57: -20878 | H57: -33115 | I57: -25672 | J57: -4444 | K57: -15417 | L57: -22781 | M57: -49982 | N57: -23166
B58: Fixed assets purchased | C58: -31962 | D58: -31503 | E58: -16072 | F58: -35079 | G58: -35304 | H58: -29702 | I58: -20205 | J58: -15168 | K58: -19230 | L58: -31414 | M58: -38042 | N58: -36282
B59: Fixed assets sold | C59: 74 | D59: 59 | E59: 53 | F59: 30 | G59: 67 | H59: 171 | I59: 351 | J59: 230 | K59: 285 | L59: 231 | M59: 974 | N59: 46
... B78: Net Cash Flow | C78: 4500 | D78: -2589 | E78: -3167 | F78: 730 | G78: 6843 | H78: -3092 | I78: 13232 | J78: 6459 | K78: -6272 | L78: 8128 | M78: -5666 | N78: -11469

Sheet Cash Flow Data
C2: 40603 | D2: 40969 | E2: 41334 | F2: 41699 | G2: 42064 | H2: 42430 | I2: 42795 | J2: 43160 | K2: 43525 | L2: 43891 | M2: 44256 | N2: 44621
B3: Cash from Operating Activity - | C3: 11240 | D3: 18384 | E3: 22163 | F3: 36151 | G3: 35531 | H3: 37900 | I3: 30199 | J3: 23857 | K3: 18891 | L3: 26633 | M3: 29001 | N3: 14283
B4: Profit from operations | C4: 16680 | D4: 22432 | E4: 24406 | F4: 36303 | G4: 43397 | H4: 38626 | I4: 28840 | J4: 33312 | K4: 28771 | L4: 23352 | M4: 31198 | N4: 26666
B5: Receivables | C5: -1422 | D5: -6659 | E5: -5177 | F5: 445 | G5: -3179 | H5: -2223 | I5: -4152 | J5: -10688 | K5: -9109 | L5: 9950 | M5: -5505 | N5: 337
B6: Inventory | C6: -2411 | D6: -2719 | E6: -2656 | F6: -2853 | G6: -3692 | H6: -5743 | I6: -6621 | J6: -3560 | K6: 2069 | L6: 2326 | M6: 3814 | N6: 597
B7: Payables | C7: 344 | D7: 5867 | E7: 8132 | F7: 4694 | G7: 3598 | H7: 3947 | I7: 9301 | J7: 7320 | K7: -4692 | L7: -8085 | M7: 5748 | N7: -7012
B8: Loans Advances | C8: 0 | D8: 0 | E8: 0 | F8: 0 | G8: 0 | H8: -520 | I8: 0 | J8: 0 | K8: 0 | L8: 0 | M8: 0 | N8: 0
B9: Other WC items | C9: -559 | D9: 1231 | E9: -303 | F9: 1870 | G9: -398 | H9: 5852 | I9: 4727 | J9: 494 | K9: 4512 | L9: 875 | M9: -4150 | N9: -4396
B10: Working capital changes | C10: -4048 | D10: -2280 | E10: -3 | F10: 4157 | G10: -3672 | H10: 1313 | I10: 3254 | J10: -6434 | K10: -7221 | L10: 5065 | M10: -93 | N10: -10474
B11: Direct taxes | C11: -1391 | D11: -1768 | E11: -2240 | F11: -4308 | G11: -4194 | H11: -2040 | I11: -1895 | J11: -3021 | K11: -2659 | L11: -1785 | M11: -2105 | N11: -1910
B12: Cash from Investing Activity - | C12: -7023 | D12: -19464 | E12: -22969 | F12: -27991 | G12: -36232 | H12: -36694 | I12: -39571 | J12: -25139 | K12: -20878 | L12: -33115 | M12: -25672 | N12: -4444
B13: Fixed assets purchased | C13: -8124 | D13: -13876 | E13: -18863 | F13: -26975 | G13: -31962 | H13: -31503 | I13: -16072 | J13: -35079 | K13: -35304 | L13: -29702 | M13: -20205 | N13: -15168
B14: Fixed assets sold | C14: 11 | D14: 93 | E14: 37 | F14: 50 | G14: 74 | H14: 59 | I14: 53 | J14: 30 | K14: 67 | L14: 171 | M14: 351 | N14: 230
... B35: Net Cash Flow | C35: 2815 | D35: 5488 | E35: -2499 | F35: 4277 | G35: 4500 | H35: -2589 | I35: -3167 | J35: 730 | K35: 6843 | L35: -3092 | M35: 13232 | N35: 6459
